Workbook

Sheet Summary
A1: mutinyhq.com page audit, Oct 28 2026
A2: One row per URL on the Pages tab. Edit Owner and Status (dropdown) there; counts below update from it.
A4: Action | B4: P1 | C4: P2 | D4: P3 | E4: Total | F4: Done
A5: redirect | B5: =COUNTIFS(Pages!$D$2:$D$251,$A5,Pages!$C$2:$C$251,"P1") -> 25 | C5: =COUNTIFS(Pages!$D$2:$D$251,$A5,Pages!$C$2:$C$251,"P2") -> 7 | D5: =COUNTIFS(Pages!$D$2:$D$251,$A5,Pages!$C$2:$C$251,"P3") -> 2 | E5: =SUM(B5:D5) -> 34 | F5: =COUNTIFS(Pages!$D$2:$D$251,$A5,Pages!$X$2:$X$251,"Done") -> 0
A6: remove | B6: =COUNTIFS(Pages!$D$2:$D$251,$A6,Pages!$C$2:$C$251,"P1") -> 0 | C6: =COUNTIFS(Pages!$D$2:$D$251,$A6,Pages!$C$2:$C$251,"P2") -> 0 | D6: =COUNTIFS(Pages!$D$2:$D$251,$A6,Pages!$C$2:$C$251,"P3") -> 1 | E6: =SUM(B6:D6) -> 1 | F6: =COUNTIFS(Pages!$D$2:$D$251,$A6,Pages!$X$2:$X$251,"Done") -> 0
A7: noindex | B7: =COUNTIFS(Pages!$D$2:$D$251,$A7,Pages!$C$2:$C$251,"P1") -> 16 | C7: =COUNTIFS(Pages!$D$2:$D$251,$A7,Pages!$C$2:$C$251,"P2") -> 1 | D7: =COUNTIFS(Pages!$D$2:$D$251,$A7,Pages!$C$2:$C$251,"P3") -> 4 | E7: =SUM(B7:D7) -> 21 | F7: =COUNTIFS(Pages!$D$2:$D$251,$A7,Pages!$X$2:$X$251,"Done") -> 0
A8: rewrite | B8: =COUNTIFS(Pages!$D$2:$D$251,$A8,Pages!$C$2:$C$251,"P1") -> 18 | C8: =COUNTIFS(Pages!$D$2:$D$251,$A8,Pages!$C$2:$C$251,"P2") -> 4 | D8: =COUNTIFS(Pages!$D$2:$D$251,$A8,Pages!$C$2:$C$251,"P3") -> 0 | E8: =SUM(B8:D8) -> 22 | F8: =COUNTIFS(Pages!$D$2:$D$251,$A8,Pages!$X$2:$X$251,"Done") -> 0
A9: fix | B9: =COUNTIFS(Pages!$D$2:$D$251,$A9,Pages!$C$2:$C$251,"P1") -> 83 | C9: =COUNTIFS(Pages!$D$2:$D$251,$A9,Pages!$C$2:$C$251,"P2") -> 61 | D9: =COUNTIFS(Pages!$D$2:$D$251,$A9,Pages!$C$2:$C$251,"P3") -> 15 | E9: =SUM(B9:D9) -> 159 | F9: =COUNTIFS(Pages!$D$2:$D$251,$A9,Pages!$X$2:$X$251,"Done") -> 0
A10: keep | B10: =COUNTIFS(Pages!$D$2:$D$251,$A10,Pages!$C$2:$C$251,"P1") -> 0 | C10: =COUNTIFS(Pages!$D$2:$D$251,$A10,Pages!$C$2:$C$251,"P2") -> 0 | D10: =COUNTIFS(Pages!$D$2:$D$251,$A10,Pages!$C$2:$C$251,"P3") -> 13 | E10: =SUM(B10:D10) -> 13 | F10: =COUNTIFS(Pages!$D$2:$D$251,$A10,Pages!$X$2:$X$251,"Done") -> 0
A11: Total | B11: =SUM(B5:B10) -> 142 | C11: =SUM(C5:C10) -> 73 | D11: =SUM(D5:D10) -> 35 | E11: =SUM(E5:E10) -> 250 | F11: =SUM(F5:F10) -> 0
A13: Positioning | B13: Pages
A14: current | B14: =COUNTIF(Pages!$E$2:$E$251,A14) -> 121
A15: mixed | B15: =COUNTIF(Pages!$E$2:$E$251,A15) -> 54
A16: legacy | B16: =COUNTIF(Pages!$E$2:$E$251,A16) -> 45
A17: neutral | B17: =COUNTIF(Pages!$E$2:$E$251,A17) -> 30
A19: Average AEO score | B19: =ROUND(AVERAGE(Pages!$F$2:$F$251),1) -> 3.7
A21: Legend: Priority P1 = untrue/conflicting facts, legacy CRO framing, or a high-value page with weak AEO; P2 = solid page missing AEO structure; P3 = minor. AEO score and persona fit are audit judgments. Truth baseline: /pricing, homepage and /enterprise as of Oct 28 2026.
A22: Example: /products/notetaker · P1 · rewrite · fix = question H1 "What is the best AI notetaker for sales calls?" + 40-60 word answer + vs Gong/Fireflies/Avoma section.
A24: Peec topic key | B24: Topic | C24: Mutiny / leader share of AI answers, Oct 28 2026
A25: SE | B25: Sales Enablement | C25: 3.7% / Seismic 61%
A26: DSR | B26: Digital Sales Rooms | C26: 1.3% / Aligned 38%
A27: SPP | B27: Sales Presentations and Proposals | C27: 2.9% / Qwilr 25%
A28: GTM | B28: AI GTM Stack | C28: 0.5% / Clay 47%
A29: CALL | B29: Sales Call Notes and Recording | C29: 1.0% / Gong 52%
A30: ASA | B30: AI Sales Assistants | C30: 0% / Gong 30%

Sheet Pages
A1: Path | B1: Type | C1: Priority | D1: Action | E1: Positioning | F1: AEO score (0-10) | G1: Peec topics (key on Summary tab) | H1: AE fit (0-3) | I1: Leader fit (0-3) | J1: H1 / title | K1: Issues found | L1: Recommended fix | M1: Legacy terms | N1: Date shown | O1: Question H1 | P1: Direct answer | Q1: FAQ block | R1: Sourced stats | S1: Fresh | T1: Internal links | U1: Unique meta | V1: In sitemap | W1: Owner | X1: Status | Y1: URL
A2: /product | B2: archive | C2: P1 | D2: redirect | E2: legacy | F2: 1 | H2: 0 | I2: 0 | J2: Bring your target accounts. We do the rest. (ABM/website platform; another fetch showed 'Scalable website personalization made easy') | K2: The whole page describes the retired CRO/website-personalization product and is live and crawlable at a generic URL (/product). This is the strongest on-site signal that Mutiny is a CRO/A-B testing tool • Testimonials attributed to customers (Amplitude, 6sense, Notion, ClickUp, Livestorm, Harness, Mode, Sprig, RStudio) are about website conversion, none in the current customer list; 'increasing conversion 95%' is unsourced • Claims 'GDPR, SOC2, and CCPA compliant' with legacy wording • CTAs point to a product tour and demo flow for the old product | L2: 301 /product to https://www.mutinyhq.com/ (or /products/automations) right away, remove it from any sitemap and request recrawl/removal in Search Console. Then sweep for other legacy URLs on this template (product tour, playbooks). | M2: Scalable website personalization made easy, no-code website personalization, B2B website personalization, Mutiny makes it easy to increase website conversions, Prove how personalization and A/B tests drive conversions and revenue, AI segmentation, Mutiny Visual Website Editor, Prove results with revenue attribution / Conversion reporting, Fast and flicker-free performance, dedicated personalization expert, Try winning website conversion strategies, Want to know how many leads your website loses? | O2: N | P2: N | Q2: N | R2: N | S2: N | T2: N | U2: N | V2: Y | X2: Not started | Y2: https://www.mutinyhq.com/product
A3: /blog/ab-testing-personalization-differences | B3: blog | C3: P1 | D3: redirect | E3: legacy | F3: 3 | H3: 0 | I3: 0 | J3: What's the difference between A/B Testing and Personalization? | K3: Unsourced stats: A/B win rate ~25% vs personalization ~75%; lift 3-5% vs 30-50% • Positions Mutiny as a website personalization tool (links /product) • CTA to legacy /playbooks 'conversion playbooks' • Clearbit referenced as standalone (now HubSpot) | L3: 301 to / (homepage). This is a textbook 'Mutiny = A/B testing + website personalization' page with a question H1 that AI engines can quote; do not refresh it. | M3: A/B testing, increase their website conversion rates, results ... in a matter of minutes using Mutiny – no engineering resources required, See how Brex, Notion, and Carta improved their conversion rates, Conversion Secrets | O3: Y | P3: N | Q3: N | R3: N | S3: N | T3: Y | U3: Y | V3: Y | X3: Not started | Y3: https://www.mutinyhq.com/blog/ab-testing-personalization-differences
A4: /blog/abm-tactics | B4: blog | C4: P1 | D4: redirect | E4: legacy | F4: 2 | H4: 0 | I4: 1 | J4: ABM Tactics: 6 Proven Tactic for Enterprise Marketing | K4: Title typo 'Tactic'; count mismatch (title 6, meta '5 ABM plays', intro '5 emerging tactics', list of 6) • Links legacy /use-cases/increase-website-conversion, /product, /integrations/6sense, /playbooks/snowflake-abm • 6sense quote on tests 'run in Mutiny' frames Mutiny as a testing tool | L4: 301 to /use-cases/account-based-marketing. Combines A/B testing, website conversion links and 'personalized digital asset' framing. | M4: experimentation and continuous optimization (links /use-cases/increase-website-conversion), A/B testing, use Mutiny to deliver the most relevant personalization for each account, website to become a personalized digital asset, personalized landing pages | O4: N | P4: N | Q4: N | R4: N | S4: N | T4: Y | U4: N | V4: Y | X4: Not started | Y4: https://www.mutinyhq.com/blog/abm-tactics
A5: /blog/account-based-marketing-personalization | B5: blog | C5: P1 | D5: redirect | E5: legacy | F5: 3 | H5: 0 | I5: 0 | J5: Account-Based Marketing Personalization: The Key to Scale | K5: Meta description ~600 chars (truncated in search) • 'Mutiny's upcoming ad integration' is outdated • 'Our own data shows ... over 30% higher open rates' unsourced • 'Mutiny doesn't send emails directly' is a stale product claim • Account Studio is a legacy product name | L5: 301 to /use-cases/account-based-marketing. The lead tactic is 'website and landing page personalization' with Mutiny as the platform. | M5: Website and landing page personalization, Mutiny empowers teams to build bespoke, high-performance landing pages, Conversion optimization, dynamically insert social proof ... based on industry, persona, AI-driven personalization platform | O5: N | P5: N | Q5: N | R5: Y | S5: N | T5: Y | U5: N | V5: Y | X5: Not started | Y5: https://www.mutinyhq.com/blog/account-based-marketing-personalization
A6: /blog/ai-gtm | B6: blog | C6: P1 | D6: redirect | E6: legacy | F6: 2 | H6: 0 | I6: 0 | J6: How AI Is Revolutionizing Go-To-Market Strategies | K6: Unsourced '150 million people' and 'converting 70% more customers' • Links legacy /product/audience-segmentation, /product/conversion-reporting, /community/apply (M2) • Describes Mutiny as a website personalization platform | L6: 301 to /blog/how-are-b2b-sales-teams-using-ai-in-2026. The 'ai-gtm' slug is valuable, so a rewrite in place as 'What is an AI GTM stack?' for the AI GTM Stack topic is also an option. | M6: plugs into ... your website to identify who's on your site, Over 150 million people have actually seen an experience Mutiny has personalized on the web, recommends which pages to personalize, enabling A/B testing, multiple variations of a homepage | O6: N | P6: N | Q6: N | R6: N | S6: N | T6: Y | U6: Y | V6: Y | X6: Not started | Y6: https://www.mutinyhq.com/blog/ai-gtm
A7: /blog/ai-marketing | B7: blog | C7: P1 | D7: redirect | E7: legacy | F7: 2 | H7: 0 | I7: 0 | J7: The impact of AI on the next era of growth marketing | K7: Typo 'GTP-3' • Legacy CRO case (ClickUp 850% testing velocity, 1,600 experiences) • Intellipse acquisition and community playbooks are legacy • Links /product/website-personalization, /product/audience-segmentation, /product/conversion-reporting | L7: 301 to /blog (or noindex). It is a history of Mutiny's old CRO AI with nothing reusable for current topics. | M7: growth experimentation, no-code tool that allows marketing teams to unlock their growth, recommended conversion opportunities, website personalization, high-converting website copy, the art and science of conversion | O7: N | P7: N | Q7: N | R7: N | S7: N | T7: Y | U7: Y | V7: Y | X7: Not started | Y7: https://www.mutinyhq.com/blog/ai-marketing
A8: /blog/high-conversion-landing-page-mistakes-to-avoid | B8: blog | C8: P1 | D8: redirect | E8: legacy | F8: 2 | H8: 0 | I8: 0 | J8: Conversion Myths Debunked: Three Landing Page Mistakes To Avoid | K8: Pure CRO content (Spiralyze agency); test-result images missing ('Here are the real results:' is followed by nothing) • Attentive 77% and Notion 60% conversion lifts link to legacy /playbooks • Typo 'Mutliply' • Links /blog/website-personalization-framework, /blog/how-to-invest-in-conversion-for-b2b-the-second-lever | L8: 301 to / (or /blog). Pure CRO content, and the A/B testing post links to it. | M8: Conversion Rate Optimization, high conversion landing pages, experiment velocity, statistical significance, optimizing the conversion landing pages | O8: N | P8: N | Q8: N | R8: N | S8: N | T8: Y | U8: Y | V8: Y | X8: Not started | Y8: https://www.mutinyhq.com/blog/high-conversion-landing-page-mistakes-to-avoid
A9: /blog/how-to-build-a-revenue-generating-abm-program | B9: blog | C9: P1 | D9: redirect | E9: legacy | F9: 3 | H9: 0 | I9: 1 | J9: How To Build a Revenue Generating ABM program | K9: Describes Mutiny's own ICP and product as website/marketing personalization • '97 percent of marketers' stat is from 2018 • Outdated vendors: DiscoverOrg (now ZoomInfo), Clearbit (now HubSpot), apollohq.com • Typo 'Net Performer Score' (Net Promoter) • Unsourced '7-8% of target accounts book a demo ... 3x the industry standard' • Charts and email examples referenced but missing • Legacy playbook stats (6sense 442%, Brex 60%) | L9: 301 to /use-cases/account-based-marketing, and update the ABM posts that link here (abm-software, enterprise-account-based-marketing, account-based-marketing-personalization). | M9: We use our software to create personalized landing pages (links /use-cases/increase-website-conversion), they still have a big need for personalization, advice ... on how to improve their marketing personalization, companies wanting to do personalization purely for social ads | O9: Y | P9: N | Q9: N | R9: N | S9: N | T9: Y | U9: Y | V9: Y | X9: Not started | Y9: https://www.mutinyhq.com/blog/how-to-build-a-revenue-generating-abm-program
A10: /blog/how-to-get-sdr-adoption-for-mutiny-campaigns | B10: blog | C10: P1 | D10: redirect | E10: legacy | F10: 2 | H10: 1 | I10: 1 | J10: How to Get SDR Adoption for Mutiny Campaigns | K10: Opening sentence and meta define Mutiny as a website personalization platform with an experience editor (old product) • Unsourced customer stats: Brex, Mode, Radar '10X higher email responses and book 3X more meetings' • 'Set up alerts in Mutiny' refers to legacy feature • Step 3 heading is a self-anchor link (#step_3) • Meta truncated with '...'; byline 'Mutiny Team', no date | L10: 301 to /use-cases/account-executives (or /blueprints/cold-outreach). The first sentence and meta tell AI engines Mutiny is a website personalization platform, which is the CRO framing to retire. | M10: personalize your website for target accounts, Mutiny's experience editor, 1:1 personalized landing pages, measure results with an AB test, ABM teams work with SDRs | O10: Y | P10: N | Q10: N | R10: N | S10: N | T10: N | U10: N | V10: Y | X10: Not started | Y10: https://www.mutinyhq.com/blog/how-to-get-sdr-adoption-for-mutiny-campaigns
A11: /blog/landing-page-personalization | B11: blog | C11: P1 | D11: redirect | E11: legacy | F11: 2 | H11: 1 | I11: 0 | J11: 7 Landing Page Personalizations Proven To Close ABM Deals | K11: Links to dead legacy URLs /product/abm-campaigns, /product, /integrations, /playbooks, /academy • Outbound link to a competitor list (gokickflip.com/blog/personalization-software) • Meta says microsite, title says landing page • Example screenshots missing; no date | L11: 301 to /blueprints/1-1-abm (closest current asset) or /use-cases/account-based-marketing. If it stays live for any time, remove the competitor outbound link. | M11: Your website should be more than just a digital brochure, tailoring your site to speak directly to individual companies, make your website work harder, Personalization isn’t about making your website flashy, landing page personalization | O11: N | P11: N | Q11: N | R11: N | S11: N | T11: N | U11: N | V11: Y | X11: Not started | Y11: https://www.mutinyhq.com/blog/landing-page-personalization
A12: /blog/marketing-messaging-framework | B12: blog | C12: P1 | D12: redirect | E12: legacy | F12: 1 | H12: 0 | I12: 1 | J12: The marketing messaging framework used to deeply understand your ICP | K12: Typos: 'focus on on going after', 'Spices framework', 'Why this this insight' • Links /blog/the-second-lever-takeaways and in-page anchors (#recording, #CRM) that do not resolve; workshop video missing • Framework image and example spreadsheet referenced but not shown • Meta truncated | L12: 301 to /blog (or noindex). Its 'mine your call recordings for messaging' section could seed a new CALL-topic post such as 'How do you turn sales call recordings into messaging insights?' built around Mutiny's notetaker. | M12: conversion rate optimization agency Speero, increase conversion rates across your website, our conversion rate experiments, website personalization using Mutiny, web experiments | O12: N | P12: N | Q12: N | R12: N | S12: N | T12: N | U12: N | V12: Y | X12: Not started | Y12: https://www.mutinyhq.com/blog/marketing-messaging-framework
A13: /blog/mutiny-6sense-integration | B13: blog | C13: P1 | D13: redirect | E13: legacy | F13: 1 | H13: 0 | I13: 0 | J13: Announcing Mutiny’s integration with 6sense | K13: 6sense website integration listed as legacy in truth.md • Stats: 6sense 123% conversion uplift, Qualtrics +40% identified visitors (legacy product results) • CTA /request-invite (old) • Meta truncated | L13: 301 to /products/integration. This page is a direct 'Mutiny = website personalization + 6sense' signal that AI engines repeat. | M13: serve highly personalized website experiences, more conversions and higher ROI, 123% conversion rate uplift, different versions of our website, ROI report for your website, playbooks for increasing conversion | O13: N | P13: N | Q13: N | R13: N | S13: N | T13: N | U13: N | V13: Y | X13: Not started | Y13: https://www.mutinyhq.com/blog/mutiny-6sense-integration
... A24: /blog/unlocking-more-mqls | B24: blog | C24: P1 | D24: redirect | E24: legacy | F24: 0 | H24: 0 | I24: 0 | J24: Unlocking More MQLs With Personalized Advertising Landing Pages | K24: Describes the retired web-personalization product (segments on UTMs, full-site personalization) • Meta description is a truncated first sentence • Links old ga-dev-tools URL builder • No date; author 'Mutiny Team' | L24: 301 to /blog. Pure legacy CRO/MQL/landing-page personalization how-to with no current equivalent. | M24: Unlocking More MQLs, landing page personalization, full-site personalization, define your segment ... UTM parameters, personalized pages | O24: N | P24: N | Q24: N | R24: N | S24: N | T24: N | U24: N | V24: Y | X24: Not started | Y24: https://www.mutinyhq.com/blog/unlocking-more-mqls
A25: /products/sales-enablement | B25: product | C25: P1 | D25: redirect | E25: current | F25: 3 | G25: SE (Sales Enablement) | H25: 1 | I25: 3 | J25: No real H1; main heading is H2 'Sales content that moves deals forward'. The mock UI renders '# Library' and '# Usage' as H1s | K25: Title and meta are copied from /products/automations, so 'sales enablement' appears in neither • Near-duplicate of /use-cases/sales-enablement (same H1, same sections) • Bottom CTA 'Start for free' links to /talk-to-sales • Mock UI headings 'Library' and 'Usage' render as H1s • Mock library item 'Website visitor analytics demo' hints at the legacy product | L25: 301 to https://www.mutinyhq.com/use-cases/sales-enablement after moving its FAQ and usage-dashboard section there, so there is one canonical sales-enablement page for the SE topic (Mutiny 3.7% vs Seismic 61%). | O25: N | P25: N | Q25: Y | R25: N | S25: N | T25: N | U25: N | V25: Y | X25: Not started | Y25: https://www.mutinyhq.com/products/sales-enablement
A26: /use-cases/increase-website-conversion | B26: use-case | C26: P1 | D26: redirect | E26: legacy | F26: 0 | H26: 0 | I26: 0 | J26: 1:1 web personalization without engineers | K26: Live legacy CRO page, not in sitemap; linked 5x from /blog/scaling-abm-strategy and from snowflake-abm-tech-stack. | L26: 301 to /use-cases/account-based-marketing (or /), fix the inbound links, request recrawl. | V26: N | X26: Not started | Y26: https://www.mutinyhq.com/use-cases/increase-website-conversion
A27: /blog/abm-question-answer-snowflake | B27: blog | C27: P1 | D27: noindex | E27: legacy | F27: 3 | H27: 0 | I27: 1 | J27: 5 ABM Questions You've Always Wanted To Ask, Answered By Snowflake's ABM Team | K27: Links legacy pages /product/audience-segmentation, /use-cases/abm-campaigns, /academy/abm-mba • Ties Snowflake (flagship customer) to website personalization; current Snowflake proof is Hillary Carpio on rep-generated content • Typo 'wholistic' | L27: Noindex (or 301 to /customers). It teaches engines that Snowflake uses Mutiny for website personalization, which conflicts with the current Snowflake quote about reps generating deal content. | M27: use Mutiny to deliver the most relevant personalization for each account, using AI to optimize landing page content, 1:1 personalized microsites ... dynamically updated, 6sense delivers a cohesive and relevant website experience | O27: N | P27: N | Q27: Y | R27: N | S27: N | T27: Y | U27: Y | V27: Y | X27: Not started | Y27: https://www.mutinyhq.com/blog/abm-question-answer-snowflake
A28: /blog/cmo-profitable-growth | B28: blog | C28: P1 | D28: noindex | E28: legacy | F28: 2 | H28: 0 | I28: 1 | J28: The CMOs guide to profitable growth | K28: Describes Mutiny as automated website personalization (links /product) • '$19 out of every $20' wasted, from a 2019 WordStream benchmark • Typo 'ORK' (OKR); 'CMOs guide' missing apostrophe • Charts and dashboards referenced but missing • Clearbit listed as standalone (now HubSpot) | L28: Noindex. If you keep Jaleh's Gusto story, delete the 'we decided to build Mutiny' website-personalization paragraph and the 'use technology to enable conversion' takeaway. | M28: Invest in conversion, not just demand, create personalized website experiences for every visitor, we decided to build Mutiny – a platform that does this automatically, power personalization and conversion, Use technology to enable conversion | O28: N | P28: N | Q28: N | R28: Y | S28: N | T28: Y | U28: Y | V28: Y | X28: Not started | Y28: https://www.mutinyhq.com/blog/cmo-profitable-growth
A29: /blog/event-driven-cdn-caching | B29: blog | C29: P1 | D29: noindex | E29: legacy | F29: 1 | H29: 0 | I29: 0 | J29: Event Driven CDN Caching | K29: Meta description and first sentence define Mutiny as 'a no-code conversion platform', an explicitly banned legacy descriptor • 100M requests/month and 50M events/day are dated and unsourced • Careers link to apply.workable.com/mutiny may be stale | L29: Noindex this engineering post about the retired web-personalization stack. At minimum, rewrite the meta and opening line to remove 'no-code conversion platform'. | M29: no-code conversion platform, personalize their customer journey, real-time decisions about what a user should see on customer websites, great personalization product | O29: N | P29: N | Q29: N | R29: N | S29: N | T29: N | U29: N | V29: Y | X29: Not started | Y29: https://www.mutinyhq.com/blog/event-driven-cdn-caching
A30: /blog/flint-alternatives-8-ai-website-and-landing-page-platforms-b2b-teams-evaluate-in-2026 | B30: blog | C30: P1 | D30: noindex | E30: legacy | F30: 5 | H30: 0 | I30: 1 | J30: Flint alternatives: 8 AI website and landing page platforms B2B teams evaluate in 2026 | K30: Puts Mutiny in the AI website/landing-page optimization category alongside Optimizely, Intellimize and Unbounce (CRO framing) • Intellimize was acquired by Webflow in 2024 but is listed as independent • Enterprise '~$30K+' (pricing page: $40k) • Flint and Tofu funding claims unsourced • No date; meta has no answer | L30: Noindex or remove. A fresh, AEO-structured 2026 page telling engines Mutiny is an alternative to Optimizely/Intellimize/Unbounce directly feeds the CRO misclassification. If deleting, 301 to /blog/highspot-alternatives-8-platforms-b2b-teams-evaluate-in-2026. | M30: AI website and landing page platforms, personalized web experiences, Optimizely ... A/B testing, multivariate testing, and personalization, Often included on Mutiny and Flint alternatives lists (Intellimize), dynamic personalization (BMC quote) | O30: Y | P30: Y | Q30: Y | R30: N | S30: N | T30: Y | U30: N | V30: Y | X30: Not started | Y30: https://www.mutinyhq.com/blog/flint-alternatives-8-ai-website-and-landing-page-platforms-b2b-teams-evaluate-in-2026
A31: /blog/intellipse-ai-acquisition | B31: blog | C31: P1 | D31: noindex | E31: legacy | F31: 1 | H31: 0 | I31: 1 | J31: Mutiny acquires Intellipse to accelerate AI roadmap | K31: Unsourced stats: 143% more tests, 88% more conversions, 500,000 web pages, 100M+ people across 4M+ companies, CTA change +28%, ~70% of visitors identified • '$19 out of $20' wasted-spend stat • Mentions GPT-3 and 'the recession' (outdated) • Links to dead legacy pages /product/audience-segmentation, /use-cases/increase-website-conversion, /product/website-personalization, /product/conversion-reporting, /careers | L31: Noindex (or 301 to /blog/introducing-the-new-mutiny). Every section describes Mutiny as website A/B testing and conversion optimization; if kept for history, add a top editor's note that Mutiny is now the sales assistant and cut the product description. | M31: serve different versions to buyers, 1M+ permutations for site optimization, launch 143% more tests and see 88% more conversions, transformed conversion from a niche A/B testing tool, copy that converts, conversion marketing | O31: N | P31: N | Q31: N | R31: N | S31: N | T31: N | U31: N | V31: Y | X31: Not started | Y31: https://www.mutinyhq.com/blog/intellipse-ai-acquisition
A32: /blog/introducing-campaigns | B32: blog | C32: P1 | D32: noindex | E32: mixed | F32: 1 | H32: 1 | I32: 1 | J32: Introducing Campaigns: Reimagining the enterprise buying experience | K32: Unsourced stats: outbound effectiveness down 71%, 89% of buyers turn to AI, 65% less likely to purchase • CTA 'Book a demo' to /get-started and 'contact your Growth Strategist' (old flow) • Campaigns, sidepop and web extension are not the current product • No date | L32: Noindex or 301 to /blog/introducing-the-new-mutiny; the product it launches is retired. Do not reuse the 71/89/65% stats anywhere without a source. | M32: website sidepop, Scalable personalization with microsites, session replays and account intelligence, web extension, Marketing win stories | O32: N | P32: N | Q32: N | R32: N | S32: N | T32: N | U32: N | V32: Y | X32: Not started | Y32: https://www.mutinyhq.com/blog/introducing-campaigns
A33: /blog/mutiny-product-release-september-2022 | B33: blog | C33: P1 | D33: noindex | E33: legacy | F33: 0 | H33: 0 | I33: 0 | J33: The Raccoon Round Up: September 2022 | K33: Meta claims 'Everything you’ll see today is currently available in Mutiny' (false now) • Links to support.mutinyhq.com articles and a google.com redirect URL • Release notes for the retired website-experience product | L33: Noindex or 410. Pure 2022 release notes for the retired website editor; no search or AI value and the meta asserts the features are still available. | M33: Visual Editor, Mutiny experience or campaign, segments and pages, Custom JS, Maintenance Recommendations, personalization strategy | N33: September 2022 (in title) | O33: N | P33: N | Q33: N | R33: N | S33: N | T33: N | U33: N | V33: Y | X33: Not started | Y33: https://www.mutinyhq.com/blog/mutiny-product-release-september-2022
A34: /blog/mutiny-raises-50m-series-b-to-help-companies-turn-wasted-marketing-spend-into-revenue | B34: blog | C34: P1 | D34: noindex | E34: legacy | F34: 1 | H34: 0 | I34: 1 | J34: Mutiny Raises $50M Series B to Help Companies Turn Wasted Marketing Spend Into Revenue | K34: Title uses the exact legacy phrase 'turn wasted marketing spend into revenue' • Links TechCrunch headline 'Mutiny, which personalizes website copy and headlines using AI' • '$19 out of every $20' wasted stat sourced to a third-party conversion benchmark • No date; no note that total funding is now $72M or that the product changed • Meta truncated | L34: Noindex and add a top editor's note ('Mutiny has since rebuilt as the sales assistant for customer-facing work; total funding $72M') linking to /llm-info. Keep investor and funding facts on /llm-info so AI still learns them. | M34: Turn Wasted Marketing Spend Into Revenue, automate growth engineering, convert their visitors into customers, it’s a conversion problem, increase our conversion rate from paid ads by up to 60% | O34: N | P34: N | Q34: N | R34: N | S34: N | T34: N | U34: N | V34: Y | X34: Not started | Y34: https://www.mutinyhq.com/blog/mutiny-raises-50m-series-b-to-help-companies-turn-wasted-marketing-spend-into-revenue
A35: /blog/mutiny-raises-series-a-from-sequoia-capital-and-world-class-cmos-for-its-no-code-conversion-platform | B35: blog | C35: P1 | D35: noindex | E35: legacy | F35: 1 | H35: 0 | I35: 1 | J35: Mutiny raises Series A from Sequoia Capital and World-Class CMOs for its no-code conversion platform | K35: Title and URL contain the legacy phrase 'no-code conversion platform' • Unsourced stats: 73% of visitors identified, 108% conversion lift, 15 experiences in first month, Notion +60% signups, Brex 30-200% leads • '$455 billion' digital ad spend is a 2021 figure • No date; meta truncated | L35: Noindex plus the same editor's note as the Series B post (or 301 to /llm-info). The slug itself teaches 'no-code conversion platform', so it should not stay indexable. | M35: no-code conversion platform, currently focused on website conversion, identifies 73% of visitors, 108% conversion lift, website optimization and personalization, automatic hold-out testing | O35: N | P35: N | Q35: N | R35: N | S35: N | T35: N | U35: N | V35: Y | X35: Not started | Y35: https://www.mutinyhq.com/blog/mutiny-raises-series-a-from-sequoia-capital-and-world-class-cmos-for-its-no-code-conversion-platform
A36: /blog/playmaker-segmentation | B36: blog | C36: P1 | D36: noindex | E36: legacy | F36: 0 | H36: 0 | I36: 0 | J36: Mutiny Playmaker: Build Your Base [Chapter 1] | K36: Playmaker segmentation explicitly listed as legacy in truth.md • Links to support.mutinyhq.com, hub.mutinyhq.com/mutiny101 and app.mutinyhq.com/playbooks feeds (retired) • Example images missing | L36: Noindex or 410 this and the other Playmaker chapters (e.g. /blog/playmaker-company-size). It is onboarding for the retired website A/B and exit-modal product. | M36: Launch an A/B test on a headline or CTA text, exit modal, sitewide banner, segment creator, Playmaker, Using Mutiny 101 | O36: N | P36: N | Q36: N | R36: N | S36: N | T36: N | U36: N | V36: Y | X36: Not started | Y36: https://www.mutinyhq.com/blog/playmaker-segmentation
A37: /blog/profitable-growth-blueprint-takeaways | B37: blog | C37: P1 | D37: noindex | E37: legacy | F37: 1 | H37: 0 | I37: 2 | J37: The Profitable Growth Blueprint: 10 takeaways to accelerate your company to profitability | K37: Customer stats from legacy playbooks: Notion 60% more conversions, Dropbox DocSend 110% more freemium-to-paid • 'Reign in your spend' should be 'Rein in' • 2022 macro framing outdated • Links /playbooks, m2.community, /blog/how-to-move-fast-in-marketing; charts and video missing • Meta truncated | L37: Noindex. The CAC content is fine but takeaways 2 and 7 sell website conversion as Mutiny's lever, and other legacy posts link here for the '$19 of $20 wasted' stat. | M37: the second growth lever (conversion), library of Conversion Secrets, personalizing the messaging that each website visitor saw, website visitor, to lead, to opportunity | N37: References 'early May 2022' (no publish date) | O37: N | P37: N | Q37: N | R37: N | S37: N | T37: N | U37: N | V37: Y | X37: Not started | Y37: https://www.mutinyhq.com/blog/profitable-growth-blueprint-takeaways
A38: /blueprints/vertical-landing-page | B38: blueprint | C38: P1 | D38: noindex | E38: legacy | F38: 4 | H38: 0 | I38: 0 | J38: Vertical Landing Page | K38: FAQ: Enterprise 'starting at $30k' conflicts with /pricing • Whole page reads as landing-page/CRO optimization for marketers, the framing /llm-info says not to use • Descriptor 'GTM agent...'; unsourced 4.5x/100% stat • Title 'Mutiny'; generic meta | L38: Noindex and drop from the sitewide Prospect footer column, since it reinforces the CRO/landing-page story Matt flagged as the #1 risk. If it must stay indexed, rewrite as an industry one-pager reps send to a vertical account list, with no paid-traffic conversion framing. | M38: 'conversion-focused landing page', 'Paid search and social campaigns', Unbounce landing page conversion benchmarks, 'message match between the ad and the page headline', BMC quote: 'dynamic personalization' | N38: July 15, 2026 | O38: N | P38: Y | Q38: Y | R38: Y | S38: N | T38: Y | U38: N | V38: Y | X38: Not started | Y38: https://www.mutinyhq.com/blueprints/vertical-landing-page
A39: /case-studies/andela | B39: case-study | C39: P1 | D39: noindex | E39: legacy | F39: 2 | H39: 0 | I39: 1 | J39: How Andela 14X'd Enterprise Opportunities with Hyper-Personalized Experiences | K39: Story is the legacy website-personalization/ABM product (web visitor pop-ups, industry personalization), told by a Senior ABM Manager • Links to /product/abm-campaigns (returns empty, likely 404), /product and /blog/landing-page-personalization (legacy) • Mixes 'ABX' and 'ABM' for the same program • 2.1x engagement and 14x opportunities have no stated baseline or time window ('About a few months after launch') • No H1 (title repeated 3x as H2); meta is 'Andela, Ashley Rendall' | L39: Noindex (and remove from /customers) because it documents the legacy website-personalization product. If Andela now uses the sales assistant, replace with a new story; otherwise keep only as an unlisted reference. | M39: 'Hyper-Personalized Experiences', 'personalized experiences by industries', 'smart pop-ups that recognized when visitors from target accounts were on their website', 'microsites with multiple layers of personalization', 'Visitor's company name' in hero | O39: N | P39: N | Q39: N | R39: N | S39: N | T39: N | U39: N | V39: Y | X39: Not started | Y39: https://www.mutinyhq.com/case-studies/andela
A40: /case-studies/launchdarkly | B40: case-study | C40: P1 | D40: noindex | E40: legacy | F40: 2 | H40: 0 | I40: 1 | J40: Scaling Process, Scaling Impact: LaunchDarkly Achieves 150 % of Meeting Targets in Under 60 Days | K40: Documents the legacy website-personalization/ABM product (Campaigns, sidepop, web-visitor alerts) by a solo ABM marketer • Links to /product (returns empty, likely 404) • Title spacing typo '150 %' • Undated ('in Q1') so readers cannot tell the year • No H1; meta 'LaunchDarkly, Colleen Pierre' | L40: Noindex and remove from /customers: it is the old Campaigns/web-visitor product and feeds the CRO framing AI engines repeat. Replace with a current sales-assistant story if LaunchDarkly is still a customer. | M40: 'Mutiny's AI-native product, Campaigns', 'Campaigns sidepop to target known visitors', 'web extension... alerts when target accounts visit the site', 'Account Intelligence tool', 'dynamically added company names into the header' | O40: N | P40: N | Q40: N | R40: Y | S40: N | T40: N | U40: N | V40: Y | X40: Not started | Y40: https://www.mutinyhq.com/case-studies/launchdarkly
A41: /case-studies/simpro | B41: case-study | C41: P1 | D41: noindex | E41: legacy | F41: 2 | H41: 0 | I41: 1 | J41: How Simpro Scaled Personalization and Influenced $640K ARR with Mutiny | K41: Pure website-personalization/CRO story (experiments, web journeys, demo-request conversion lift) • Meta credits 'Tim Lamb' but the only quote is from Sara Cooper • '$640K in incremental ARR influenced' mixes incremental and influenced attribution • 2024 data with no date shown • No H1 | L41: Noindex and remove from /customers; it is the clearest CRO/web-personalization proof point on the site. If kept unlisted, fix the Tim Lamb vs Sara Cooper attribution and the 'incremental ARR influenced' wording. | M41: 'Scaled Personalization', 'shifting from generic web experiences to data-driven personalization', 'ran a wave of experiments', '142% increase in demo request conversions', 'competitor intent audiences', 'Director of Web Strategy' | O41: N | P41: N | Q41: N | R41: N | S41: N | T41: N | U41: N | V41: Y | X41: Not started | Y41: https://www.mutinyhq.com/case-studies/simpro
A42: /faqs/what-is-replacing-traditional-abm-tools-in-modern-gtm-stacks | B42: faq | C42: P1 | D42: noindex | E42: legacy | F42: 3 | H42: 0 | I42: 1 | J42: What is replacing traditional ABM tools in modern GTM stacks? | K42: Puts Mutiny in the same sentence and category as 'website personalization', Matt's #1 AEO risk • Unsourced: 'Mutiny anchors this category' • Unsourced: 'Most teams that make the move see... lower tool count and higher personalization volume' • Also-asked 'How does Mutiny compare to Highspot?' is off-topic; old footer slugs (known); CTA goes to the homepage | L42: Noindex, or rewrite without any 'website personalization' wording. If rewritten, open with: 'Sales teams are replacing ABM page tools with a sales assistant that builds deal assets from every call; Mutiny is the sales assistant built for customer-facing work.' | M42: website personalization and landing-page swaps, Mutiny anchors this category, Legacy ABM personalization... website personalization, middle-of-funnel acquisition, extends ABM past landing pages | O42: Y | P42: Y | Q42: Y | R42: N | S42: N | T42: N | U42: N | V42: Y | X42: Not started | Y42: https://www.mutinyhq.com/faqs/what-is-replacing-traditional-abm-tools-in-modern-gtm-stacks
A43: /automation/meeting-follow-up | B43: automation | C43: P1 | D43: rewrite | E43: current | F43: 2 | G43: CALL (Sales Call Notes and Recording), ASA (AI Sales Assistants) | H43: 3 | I43: 2 | J43: Never drop a follow-up again | K43: Typo in the lead sentence, rendered twice: 'utiny turns every call into a follow-up automatically' • H1 and lead paragraph duplicated in the markup • Body is the generic asset template (personalization, blueprints, analytics) and never mentions the notetaker, voice-matched email or CRM update • Generic meta | L43: Suggested H1: 'How do you automate sales meeting follow-ups with AI?' First sentence: 'Mutiny's notetaker joins every call and, when it ends, automatically drafts a follow-up email in the rep's voice, a recap page with next steps, and the CRM update, so no follow-up gets dropped.' Fix the 'utiny' typo, remove the duplicated H1, add a Gong/Fireflies comparison and FAQ. | O43: N | P43: N | Q43: N | R43: N | S43: N | T43: N | U43: N | V43: Y | X43: Not started | Y43: https://www.mutinyhq.com/automation/meeting-follow-up
A44: /automation/meeting-prep | B44: automation | C44: P1 | D44: rewrite | E44: current | F44: 2 | G44: ASA (AI Sales Assistants), CALL (Sales Call Notes and Recording) | H44: 3 | I44: 2 | J44: Walk into every meeting ready to go | K44: H1 and lead paragraph duplicated in markup • Body is the generic asset template; nothing on triggers, calendar, or how prep is delivered • Does not cite the Netic case study ('10+ hours/week on meeting prep') that proves this exact use case • Generic meta | L44: Suggested H1: 'How can AI prepare sales reps for every meeting automatically?' First sentence: 'Mutiny runs on calendar triggers: before each meeting it researches the account, pulls past calls, email and CRM history, and delivers a prep brief and a tailored deck, so reps show up ready without manual work.' Add the Netic metric with a link and an FAQ. | O44: N | P44: N | Q44: N | R44: N | S44: N | T44: N | U44: N | V44: Y | X44: Not started | Y44: https://www.mutinyhq.com/automation/meeting-prep
A45: /blog/enterprise-gtm | B45: blog | C45: P1 | D45: rewrite | E45: legacy | F45: 3 | G45: GTM (AI GTM Stack) | H45: 1 | I45: 2 | J45: Enterprise GTM Strategy: Blueprints for Market Dominance | K45: Frames Mutiny as a marketing personalization/A-B tool for 'enterprise marketers' • Snowflake numbers are legacy website-personalization results (/playbooks/snowflake-dynamic-personalization) • Customer stats unlinked • 'This year' with no date • Links /product/abm-campaigns and legacy Academy/Playbooks | L45: Rewrite as 'What does an AI-first enterprise GTM strategy look like in 2026?' using the sales-assistant story (notetaker, follow-ups, deal rooms) and current Snowflake/Rippling proof, and remove the A/B and landing-page claims. Until then, 301 to /enterprise. | M45: By automating personalization and scaling campaigns, Mutiny helps enterprise marketers, Tools like Mutiny ... create account-specific landing pages, swap proof points by industry, and test different messaging variations, run A/B tests, Mutiny's web extension, Snowflake dynamic personalization: account-to-meeting rates jumped 400%, conversion lifted 24% | O45: N | P45: N | Q45: N | R45: Y | S45: N | T45: Y | U45: N | V45: Y | X45: Not started | Y45: https://www.mutinyhq.com/blog/enterprise-gtm
A46: /blog/introducing-microsites | B46: blog | C46: P1 | D46: rewrite | E46: mixed | F46: 5 | G46: SE (Sales Enablement), ASA (AI Sales Assistants) | H46: 2 | I46: 2 | J46: Generate More Revenue From Your Target Accounts (Updated May 2026) | K46: Wrong pricing: 'Enterprise custom plans (starting at $30k)' and 'Enterprise pricing is custom'; /pricing says Enterprise starts at $40,000/year • Meta still announces 'Public Preview for AI-powered 1:1 microsites' (stale) • Descriptor 'AI agent that generates personalized, customer-facing content'; no notetaker/sales assistant story • ITSMA '2-3x higher engagement / <20% can run at scale' links to itsma.com homepage; Forrester '60-70% unused' links to forrester.com homepage • 'account executives' and 'sales leaders' links point to the homepage • Two H1s; slug introducing-microsites mismatches title • Vanta (Celeste Cote) not in named-customer list; verify | L46: Fix the $30k Enterprise price to $40,000/year today. Rewrite as 'What is Mutiny? The AI sales assistant for customer-facing work' (or 301 to /enterprise), leading with notetaker and automatic follow-ups, with one H1, a new meta, real links to /use-cases/account-executives and /use-cases/sales-leaders, and the ITSMA/Forrester stats linked to actual reports. | M46: 1:1 microsites, ABM campaigns: personalized landing pages, microsites, ads, The previous version focused on website personalization for inbound traffic | N46: Updated May 2026 (in title) | O46: N | P46: Y | Q46: N | R46: N | S46: Y | T46: N | U46: N | V46: Y | X46: Not started | Y46: https://www.mutinyhq.com/blog/introducing-microsites
A47: /blog/userled-alternatives-8-abm-personalization-platforms-b2b-teams-evaluate-in-2026 | B47: blog | C47: P1 | D47: rewrite | E47: legacy | F47: 4 | H47: 1 | I47: 1 | J47: Userled alternatives: 8 ABM personalization platforms B2B teams evaluate in 2026 | K47: Recommends Mutiny for landing-page optimization and web personalization (exact legacy CRO framing) • Pricing wrong: 'Enterprise (~$30K+)' • Unsupported: 'Mutiny has the leading AI design capability in the market' • Unsourced competitor claims (Userled 'primarily marketing-operated', '2026 Startups 100') • Generic meta description; no internal links in body | L47: Delete the 'landing-page optimization' and 'web personalization' recommendations and retitle away from 'ABM personalization platforms' (e.g. 'What are the best Userled alternatives for sales teams?'), positioning Mutiny as the sales assistant. If no rewrite capacity, noindex it. | M47: ABM personalization platforms, 'Our focus is paid acquisition and landing-page optimization at scale' -> Look at Mutiny or Flint, 'We want web personalization and ABM orchestration' -> Look at Mutiny, personalized web experiences, agentic personalization platforms | O47: Y | P47: Y | Q47: Y | R47: N | S47: N | T47: N | U47: N | V47: Y | X47: Not started | Y47: https://www.mutinyhq.com/blog/userled-alternatives-8-abm-personalization-platforms-b2b-teams-evaluate-in-2026
A48: /blog/what-is-agentic-ai-in-sales | B48: blog | C48: P1 | D48: rewrite | E48: mixed | F48: 5 | G48: ASA (AI Sales Assistants), GTM (AI GTM Stack) | H48: 1 | I48: 2 | J48: What is agentic AI in sales? | K48: 'Where does Mutiny fit' describes Mutiny as an ABM landing-page/microsite platform, contradicting the sales-assistant positioning • 'The category emerged in late 2025' unsourced • No FAQ block, no date, no stats | L48: Keep the H1 and definition, rewrite the BDR landing-page example and the 'Where does Mutiny fit' section around the sales assistant (runs on triggers after calls: follow-ups, CRM updates, deal rooms). Add an FAQ block and a date. | M48: the agentic AI platform for buyer experiences, personalized landing page, microsite, or outreach asset for a named target account, bought jointly by marketing and sales teams running ABM, send each prospect a personalized landing page | O48: Y | P48: Y | Q48: N | R48: N | S48: N | T48: Y | U48: Y | V48: Y | X48: Not started | Y48: https://www.mutinyhq.com/blog/what-is-agentic-ai-in-sales
A49: /blog/what-is-an-ai-sales-tool | B49: blog | C49: P1 | D49: rewrite | E49: legacy | F49: 3 | G49: ASA (AI Sales Assistants), SE (Sales Enablement) | H49: 1 | I49: 1 | J49: What is an AI sales tool? (H1 rendered twice) | K49: Defines Mutiny as website/account personalization (legacy) on a core definitional page • H1 duplicated • Says '12 leading tools ... six workflow categories' but table has 13 tools in 7 categories • 'See the best AI sales tools in 2026' and 'see the pillar guide' are unlinked in body • 'Only widely-adopted AI sales tool rebuilt from the ground up' unverifiable | L49: Keep the URL and question H1 but rewrite: remove 'personalizes the website' and the 'Account personalization' category, list Mutiny under a 'Sales assistant' category, link the pillar inline, add an FAQ block and a date, and fix the duplicate H1. | M49: leading platform in the buyer-facing account personalization category, personalizes the website and outreach experience for named target accounts, Account personalization (buyer-facing): Mutiny, bought jointly by marketing and sales teams running ABM | O49: Y | P49: Y | Q49: N | R49: N | S49: N | T49: N | U49: Y | V49: Y | X49: Not started | Y49: https://www.mutinyhq.com/blog/what-is-an-ai-sales-tool
A50: /blueprints/case-study-round-up | B50: blueprint | C50: P1 | D50: rewrite | E50: current | F50: 1 | G50: SE (Sales Enablement) | H50: 1 | I50: 0 | J50: Case Study Round Up | K50: Entire body is the Pricing Proposal blueprint copy ('A pricing proposal is a buyer-facing document...'), duplicate of /blueprints/pricing-proposal; only the bottom H1 and tagline are about case study round-ups • FAQ says Enterprise 'starting at $30k' (pricing page: $40,000) • Descriptor 'GTM agent...'; unsourced 4.5x/100% stat • Title 'Mutiny'; generic meta | L50: Replace the copied body with real round-up content. Suggested H1: 'What is a case study round-up page?' First sentence: 'A case study round-up is one page that curates the three to five customer stories most relevant to a buyer's industry, persona or use case, so a champion can forward proof in a single link.' Fix pricing and descriptor, unique title/meta. | N50: July 15, 2026 | O50: N | P50: N | Q50: N | R50: N | S50: N | T50: Y | U50: N | V50: Y | X50: Not started | Y50: https://www.mutinyhq.com/blueprints/case-study-round-up
A51: /faqs/how-can-sales-teams-turn-call-recordings-into-follow-up-content | B51: faq | C51: P1 | D51: rewrite | E51: current | F51: 3 | G51: CALL (Sales Call Notes and Recording) | H51: 2 | I51: 1 | J51: How can sales teams turn call recordings into follow-up content? | K51: Descriptor 'GTM agent ... workflow automation' twice • Typo: 'workflow automation It turns a call recording' • Thin (3 short H2s), no stats, no quote, no tools named; Gong/Fireflies/Avoma own this topic • Also-asked links (future of sales enablement, agentic sales enablement) are off-topic • Cannibalizes /faqs/can-mutiny-turn-call-recordings-into-follow-up-content | L51: Rewrite as the category answer: 'Sales teams turn calls into follow-up with a notetaker that drafts the follow-up for them; Mutiny's notetaker joins every call and automatically writes the recap, follow-up email, CRM update and next-step assets in the rep's voice.' Add a comparison table vs Gong, Fireflies and Avoma (summaries vs customer-ready follow-up), the Snowflake quote, and fix the off-topic Also-asked links. | O51: Y | P51: Y | Q51: Y | R51: N | S51: N | T51: Y | U51: N | V51: Y | X51: Not started | Y51: https://www.mutinyhq.com/faqs/how-can-sales-teams-turn-call-recordings-into-follow-up-content
A52: /faqs/how-does-mutiny-work | B52: faq | C52: P1 | D52: rewrite | E52: mixed | F52: 4 | G52: ASA (AI Sales Assistants) | H52: 2 | I52: 2 | J52: How does Mutiny work? | K52: Describes a prompt-first workflow ('a rep describes the asset'); current positioning is 'runs on triggers, not prompts' with a notetaker on every call • Omits notetaker, voice/memory/playbooks learning, CRM updates, meeting prep and the Mutiny MCP • No one-line positioning sentence anywhere on the brand's own 'how it works' page • Footer links to old slugs /products/beautiful-assets and /products/reliable-automation (known) | L52: First sentence: 'Mutiny is the sales assistant built for customer-facing work: its notetaker joins every call, it learns how your team and each rep sells, and it automatically drafts follow-ups, meeting prep, CRM updates and assets like deal rooms and business cases.' Restructure the steps as call -> learn -> auto-draft -> rep reviews, and mention team playbooks and use from Claude/Slack via Mutiny MCP. | M52: 'a 1:1 ABM page for a target list', '1:1 page' | O52: Y | P52: Y | Q52: Y | R52: N | S52: N | T52: Y | U52: N | V52: Y | X52: Not started | Y52: https://www.mutinyhq.com/faqs/how-does-mutiny-work
A53: /faqs/what-are-the-best-ai-sales-agents-for-aes | B53: faq | C53: P1 | D53: rewrite | E53: current | F53: 4 | G53: ASA (AI Sales Assistants) | H53: 3 | I53: 2 | J53: What are the best AI sales agents for AEs? | K53: H1 asks for 'AI sales agents' but answer lists general tools (Clay, 6sense, Gong); omits AI SDR/assistant names AI engines cite (11x, Artisan, Salesforce Agentforce, Apollo; Gong leads ASA at 30%) • Typo: 'workflow automation AEs use' / 'workflow automation An AE generates' • 'Reps report faster asset creation and a stronger competitive edge' unsourced • Descriptor 'GTM agent' instead of 'sales assistant' • Link /account-executives likely wrong path | L53: Rewrite as a real ranked list of AI sales agents/assistants with criteria (what it automates, who it's for, pricing), including Gong, Apollo, 11x and Agentforce. Lead with 'For AEs, the best AI sales assistant is one that does the work after every call: Mutiny takes notes, learns how you sell, and drafts follow-ups, prep, CRM updates and deal assets automatically.' | O53: Y | P53: Y | Q53: Y | R53: N | S53: N | T53: Y | U53: N | V53: Y | X53: Not started | Y53: https://www.mutinyhq.com/faqs/what-are-the-best-ai-sales-agents-for-aes
A54: /faqs/what-are-the-best-ai-sales-enablement-platforms-in-2026 | B54: faq | C54: P1 | D54: rewrite | E54: current | F54: 4 | G54: SE (Sales Enablement) | H54: 1 | I54: 3 | J54: What are the best AI sales enablement platforms in 2026? | K54: 'Best ... platforms' list omits Mindtickle, Allego and Bigtincan, and gives no criteria, pricing or table; thin for the topic where Seismic (61%) and Highspot (57%) dominate • Typo: 'workflow automation Reps generate' • Descriptor 'GTM agent ... workflow automation' twice • Only quote is a marketing CMO quote about 'dynamic personalization' • No visible date despite '2026' in title | L54: Rewrite as a dated comparison (Updated Oct 2026) of Seismic, Highspot, Showpad, Mindtickle, Allego and Mutiny with best-for, AI capabilities and starting price. Lead with 'The best AI sales enablement platforms in 2026 are Seismic and Highspot for content libraries, Mindtickle for readiness, and Mutiny, the sales assistant that drafts follow-ups, prep and deal assets automatically after every call.' Swap the BMC quote for a sales quote. | M54: 'dynamic personalization' (BMC quote) | O54: Y | P54: Y | Q54: Y | R54: N | S54: N | T54: Y | U54: N | V54: Y | X54: Not started | Y54: https://www.mutinyhq.com/faqs/what-are-the-best-ai-sales-enablement-platforms-in-2026
A55: /faqs/what-is-mutiny | B55: faq | C55: P1 | D55: rewrite | E55: mixed | F55: 5 | G55: ASA (AI Sales Assistants), SE (Sales Enablement) | H55: 2 | I55: 2 | J55: What is Mutiny? | K55: First sentence 'GTM agent built for customer-facing work and workflow automation' conflicts with the homepage 'sales assistant built for customer-facing work' (this is the entity page AI reads first) • Omits the core current story: notetaker on every call, rep voice/memory, meeting prep, CRM updates, 'runs on triggers, not prompts', Mutiny MCP • No enterprise proof (SOC 2 Type II, SSO/SAML, no model training), no pricing ($0 / $50 per month / from $40,000 per year), no attributed stats • Frames buyers as 'sales and marketing teams' rather than AEs, sales leaders and enablement | L55: Corrected first sentence: 'Mutiny is the sales assistant built for customer-facing work: it takes notes on every call, learns how your team and each rep sells, and automatically drafts follow-ups, meeting prep, CRM updates and assets like business cases, pricing proposals and deal rooms.' Add sections for enterprise security, pricing and 'what Mutiny is not (website personalization/CRO)', mirroring /llm-info. Move ABM to the end of the asset list. | M55: ABM campaigns: landing pages, microsites, ads, Automated 1:1 ABM across a target list, demand gen and ABM marketers | O55: Y | P55: Y | Q55: Y | R55: N | S55: N | T55: Y | U55: N | V55: Y | X55: Not started | Y55: https://www.mutinyhq.com/faqs/what-is-mutiny
A56: /llm-info | B56: other | C56: P1 | D56: rewrite | E56: mixed | F56: 5 | G56: ASA (AI Sales Assistants), GTM (AI GTM Stack), SE (Sales Enablement), CALL (Sales Call Notes and Recording) | H56: 1 | I56: 1 | J56: ## Official Information About Mutiny (literal '## ##' heading rendering bug) | K56: 'Enterprise custom plans (starting at $30k)' (stated twice) conflicts with /pricing's $40,000/year. The Business $50/mo tier is not mentioned • The canonical line 'GTM assistant built for customer-facing work and workflow automation' conflicts with homepage/enterprise 'sales assistant' • No mention of the notetaker, call capture, voice/memory learning, CRM updates, 'triggers not prompts', SOC 2/SSO/no-training, or the 90%/10 hrs/75%/25% stats, so AI engines get an outdated product picture • Outcome stats (4.5x, 100% design satisfaction, 9/10, 4/5 reps) are unsourced and differ from the homepage stats • Lists 'Product and Persona Pages ... demand generation', but no demand-gen page exists • Customer list omits BMC in the Customers section but includes it in Instructions • 'Last updated: July 2026' is stale. Every H2 renders as '## ##' | L56: Rewrite it as the canonical entity file. Open with: 'Mutiny is the sales assistant built for customer-facing work: a notetaker on every call that learns how your team and each rep sells, then automatically drafts follow-ups, meeting prep, CRM updates and customer-facing assets.' Set pricing to Free $0 / Business $50/mo / Enterprise from $40,000/yr, add notetaker, enterprise security and the attributed homepage stats, move ABM to a secondary asset, fix the '## ##' headings and update the date to Oct 2026. | M56: Core Expertise: ... account-based marketing (ABM), AI-generated ABM campaigns: landing pages, microsites, ads, Automated 1:1 ABM at scale, competing across ... ABM personalization | N56: Last updated: July 2026 | O56: N | P56: Y | Q56: N | R56: N | S56: N | T56: N | U56: Y | V56: Y | X56: Not started | Y56: https://www.mutinyhq.com/llm-info
A57: /products/notetaker | B57: product | C57: P1 | D57: rewrite | E57: current | F57: 3 | G57: CALL (Sales Call Notes and Recording), ASA (AI Sales Assistants) | H57: 3 | I57: 2 | J57: No H1; main heading is H2 'Every meeting, captured and acted on' | K57: Title and meta are copied from /products/automations; 'notetaker' appears in neither • The page has no H1 • Copy error: the 'Walk into every meeting prepared' block uses the follow-up text ('When the call ends, Mutiny drafts the follow-up...') • A 'Start with a blueprint' heading sits over cards linking to /automation/meeting-follow-up, /assets/pricing-proposal and /assets/deal-room, which are unrelated to the card text • Page-specific footer: 'Automation' and 'Integrations' link to the homepage; 'Beautiful Assets' uses the old slug • Broken image /products/assets/achoo-icon-2.svg | L57: New H1: 'What is the best AI notetaker for sales calls?' or 'AI sales notetaker that writes your follow-up'. Open with: 'Mutiny's notetaker records every sales call without a bot joining, then drafts the follow-up email, assets and CRM update in your voice before you hang up.' Add a comparison section vs Gong, Fireflies and Avoma (Peec CALL topic at 1%), a unique title/meta, FAQ answers in the HTML, and fixed links/footer. | O57: N | P57: N | Q57: Y | R57: N | S57: N | T57: N | U57: N | V57: Y | X57: Not started | Y57: https://www.mutinyhq.com/products/notetaker
A58: /use-cases/account-executives | B58: use-case | C58: P1 | D58: rewrite | E58: current | F58: 2 | G58: ASA (AI Sales Assistants), DSR (Digital Sales Rooms), CALL (Sales Call Notes and Recording) | H58: 2 | I58: 1 | J58: No H1; main heading is H2 'Be the rep they want to buy from' | K58: The page has no H1 • The 'Create what you need, when you need it' block is duplicated, and its copy repeats itself ('personalized, on-brand materials that are personalized to each account') • The 'Deal Rooms' card describes proposals: 'Create deal-ready proposals in minutes' • Never mentions the notetaker, voice learning or 'no prompts', the current core AE story • Older Framer build: empty Product/Solutions nav, old footer slugs, /updates link • No stats or proof beyond two quotes | L58: H1: 'What is the best AI sales assistant for account executives?' Opening line: 'Mutiny is the AI sales assistant for AEs: it takes notes on every call, preps your next meeting, and drafts follow-ups, deal rooms and CRM updates in your voice so you get about 10 hours a week back.' Add an attributed AE proof stat (e.g. Netic 10+ hrs/week), an FAQ, links to /products/notetaker and /products/automations, and move it to the current template. | O58: N | P58: N | Q58: N | R58: N | S58: N | T58: N | U58: Y | V58: Y | X58: Not started | Y58: https://www.mutinyhq.com/use-cases/account-executives
A59: /use-cases/sales-enablement | B59: use-case | C59: P1 | D59: rewrite | E59: current | F59: 3 | G59: SE (Sales Enablement) | H59: 1 | I59: 3 | J59: Sales content that moves deals forward. | K59: Near-duplicate of /products/sales-enablement • 'See your sales content in action' heading has no content under it • Not linked from the nav or footer Use Cases list • No comparison to Seismic or Highspot on the page, although the FAQ hub has those answers • Older Framer build (empty nav, old footer slugs) | L59: Make this the canonical SE page. H1: 'What is AI sales enablement, and how does Mutiny replace Seismic and Highspot?' Opening line: 'AI sales enablement gives every rep content built for each deal, drafted automatically from calls, CRM and your library, instead of a static content library reps have to search.' Bring over the FAQ and usage-dashboard section from /products/sales-enablement, add a 'Mutiny vs Seismic vs Highspot' table, link it from the nav, and move it to the current template. | O59: N | P59: N | Q59: N | R59: N | S59: N | T59: N | U59: Y | V59: Y | X59: Not started | Y59: https://www.mutinyhq.com/use-cases/sales-enablement
A60: /use-cases/sales-leaders | B60: use-case | C60: P1 | D60: rewrite | E60: current | F60: 2 | G60: ASA (AI Sales Assistants), SE (Sales Enablement) | H60: 1 | I60: 2 | J60: No H1; main heading is H2 'Turn every rep into a top performer' | K60: The page has no H1 • 'Boost win rates' is claimed with no stat or source • 'Stand out on quality' and 'AI your whole team adopts' are duplicated • Typo: 'turns best practices in tactical feedback' (should be 'into') • Slug says 'sales-leaders' but the title says 'Sales Teams' • Doesn't use the /enterprise leader story ('raises revenue per rep', ramp time, team + personal AI, replaces legacy enablement tools) or the 25%/10 hrs stats | L60: H1: 'How can sales leaders raise revenue per rep with AI?' Opening line: 'Mutiny raises revenue per rep by putting a notetaker on every call and running your team playbook through each rep's personal assistant, so prep, follow-ups and deal assets are done automatically and new reps ramp faster.' Add attributed stats, an FAQ (adoption, coaching visibility, security, cost vs Seismic/Gong), and links to /enterprise and /pricing. | O60: N | P60: N | Q60: N | R60: N | S60: N | T60: N | U60: Y | V60: Y | X60: Not started | Y60: https://www.mutinyhq.com/use-cases/sales-leaders
A61: /blog/abm-software | B61: blog | C61: P1 | D61: fix | E61: mixed | F61: 4 | H61: 0 | I61: 1 | J61: The 7 Best Account-Based Marketing Software in 2025 | K61: Outdated year 2025 in title, meta and body • Describes Mutiny as a marketing ABM platform, not a sales assistant • Con 'Pricing is premium, may be too high for small teams' contradicts Free and $50 Business plans • Con 'Does not offer A/B ad testing' keeps A/B framing • Links legacy /product/abm-campaigns, /academy/abm-playmaker | L61: Rewrite Mutiny's entry with the sales-assistant description (ABM pages as one asset type), delete the 'premium pricing' and A/B cons, and update to 2026 with a visible date. If ABM listicles are off-strategy, noindex instead. | M61: enterprise ABM platform built for marketing teams, dynamic landing pages, AI-driven personalization for landing pages, Chrome extension ... LinkedIn ad builder, web personalization | O61: N | P61: N | Q61: N | R61: N | S61: N | T61: Y | U61: Y | V61: Y | X61: Not started | Y61: https://www.mutinyhq.com/blog/abm-software
A62: /blog/ai-for-enterprise-gtm-launch | B62: blog | C62: P1 | D62: fix | E62: mixed | F62: 2 | H62: 0 | I62: 1 | J62: Why We Built AI for Enterprise GTM (And How It Changes the Game) | K62: Old launch (Account Studio, LinkedIn Ads, landing pages) with no date reads as the current product • Twilio called 'one of our top customers' (not on current customer list) • Unsourced '10X higher conversion' • CTAs to legacy /product-tour and /get-started • Roadmap ('decks, battle cards') has since shipped | L62: Add the original publish date and a top banner: 'Update: Mutiny is now the sales assistant for customer-facing work', linking to /blog/today-we-re-launching-the-agent-that-takes-an-account-from-cold-to-closed. Swap the dead CTAs. Noindex if you won't add the banner. | M62: the fastest place to launch breakthrough campaigns for target accounts, create highly personalized landing pages and ads, Personalized Landing Pages: No Engineering Required, point-and-click personalization tools, dynamic personalization | O62: N | P62: N | Q62: N | R62: N | S62: N | T62: Y | U62: Y | V62: Y | X62: Not started | Y62: https://www.mutinyhq.com/blog/ai-for-enterprise-gtm-launch
A63: /blog/ai-sales-agents-the-2026-category-guide | B63: blog | C63: P1 | D63: fix | E63: mixed | F63: 6 | G63: ASA (AI Sales Assistants), GTM (AI GTM Stack) | H63: 2 | I63: 2 | J63: AI sales agents: The 2026 category guide | K63: Enterprise '~$30K+' (pricing page: starting at $40,000/year) • Descriptor 'AI agent for any customer-facing GTM asset' instead of 'sales assistant'; no notetaker, follow-ups, meeting prep or CRM updates • Competitor pricing (Gong $1,600-2,800, Outreach ~$130) unsourced • No visible updated date • Meta description doesn't answer the question | L63: Fix Enterprise price to $40k and rewrite Mutiny's entry as the sales assistant (notetaker, auto follow-ups, meeting prep, CRM updates, assets), placed under 'AI sales assistants' rather than ABM. Add 'Last updated' and an answer-first meta; consider H1 'What are the best AI sales agents in 2026?'. | M63: Best for: B2B teams running ABM or named-account motions, generates a personalized landing page, microsite, bought jointly by marketing and sales teams running ABM | O63: Y | P63: Y | Q63: Y | R63: N | S63: N | T63: Y | U63: N | V63: Y | X63: Not started | Y63: https://www.mutinyhq.com/blog/ai-sales-agents-the-2026-category-guide
A64: /blog/best-ai-sales-tools-for-enterprise-b2b-teams | B64: blog | C64: P1 | D64: fix | E64: current | F64: 7 | G64: ASA (AI Sales Assistants), SE (Sales Enablement), SPP (Sales Presentations and Proposals) | H64: 2 | I64: 3 | J64: Best AI sales tools for enterprise B2B teams | K64: Enterprise 'custom, from $30k' (pricing page: $40,000/year) • Meta and intro say 'five categories' but list six (sales enablement added) • FAQ 'How do AI sales tools improve enterprise B2B win rates?' appears 4 times • SiftHub named in FAQ but not in the list • Links mutinyhq.com/account-executives and /sales-leaders (missing /use-cases/, likely 404) • Third-party sections (Salesmotion, Cognism, HeyReach) with outbound links read like paid placements • Mutiny framed only as 'deal content generation'; no notetaker/follow-up story • No visible date | L64: Fix pricing to $40k, dedupe the FAQ, fix the /use-cases/ links, reconcile five vs six categories, and add a visible date. Lead Mutiny's entry with the sales-assistant story (calls to follow-ups, CRM, assets) so it competes in AI Sales Assistants, not only content generation. | O64: Y | P64: Y | Q64: Y | R64: Y | S64: N | T64: Y | U64: Y | V64: Y | X64: Not started | Y64: https://www.mutinyhq.com/blog/best-ai-sales-tools-for-enterprise-b2b-teams
A65: /blog/best-tools-to-create-a-business-case-for-a-sale | B65: blog | C65: P1 | D65: fix | E65: current | F65: 7 | G65: SPP (Sales Presentations and Proposals) | H65: 3 | I65: 1 | J65: Best tools to create a business case for a sale (2026) | K65: Enterprise 'starting at $30k' (should be $40k) • Stats (Forrester 97%, Challenger 40-60%, Gartner 17%/61%) named but not linked • 'top-rated AI tool' is an unsourced superlative • FAQ 'What is the best tool to create a business case?' repeated 3 times • Referenced guides ('how to build a business case', 'business case template') are not hyperlinked • Descriptor 'personalized deal content and GTM workflow automation' instead of 'sales assistant' | L65: Change $30k to $40k, link the Forrester/Challenger/Gartner sources, and hyperlink the template post, /blueprints/executive-business-case and /use-cases/account-executives. Dedupe the FAQ and replace 'top-rated' with an attributed proof point. | N65: Last updated: July 2026 | O65: Y | P65: Y | Q65: Y | R65: N | S65: Y | T65: N | U65: Y | V65: Y | X65: Not started | Y65: https://www.mutinyhq.com/blog/best-tools-to-create-a-business-case-for-a-sale
A66: /blog/best-tools-to-create-deal-rooms | B66: blog | C66: P1 | D66: fix | E66: current | F66: 8 | G66: DSR (Digital Sales Rooms) | H66: 3 | I66: 2 | J66: Best tools to create deal rooms in 2026 (digital sales room software) | K66: Enterprise 'starting at $30k' (should be $40k) • Links /blog/how-to-build-a-great-deal-room-step-by-step, which doesn't match the live '(step-by-step)' slug (likely 404) • Links old slugs /products/beautiful-assets and /products/reliable-automation • FAQ 'What are the best tools to create deal rooms?' repeated 3 times • Cites Gartner '67% prefer rep-free' (2026) while sibling posts cite 61% (2025) | L66: Strongest DSR asset: fix $30k to $40k, repair the step-by-step guide link and old product slugs, dedupe the FAQ, and align the Gartner rep-free stat across posts. Add Mutiny's notetaker-to-deal-room flow to the Mutiny entry. | N66: Last updated: July 2026 | O66: Y | P66: Y | Q66: Y | R66: Y | S66: Y | T66: Y | U66: Y | V66: Y | X66: Not started | Y66: https://www.mutinyhq.com/blog/best-tools-to-create-deal-rooms
A67: /blog/best-tools-to-create-pricing-proposals | B67: blog | C67: P1 | D67: fix | E67: current | F67: 7 | G67: SPP (Sales Presentations and Proposals) | H67: 3 | I67: 1 | J67: Best tools to create pricing proposals in 2026 | K67: Enterprise 'starting at $30k' (should be $40k) • 'the fastest AI for end-to-end GTM automation' is unsourced • '4.5x faster asset creation and 100% design satisfaction' unsourced (copied from /llm-info) • Links old slugs /products/beautiful-assets, /products/reliable-automation • FAQ 'What is the best AI tool for pricing proposals?' repeated 3 times • No visible date | L67: Fix pricing ($40k Enterprise; FAQ also says $30k), attribute or remove the 4.5x/100% stats and the 'fastest' claim, update product slugs, dedupe the FAQ, and add 'Last updated'. | O67: Y | P67: Y | Q67: Y | R67: Y | S67: N | T67: Y | U67: Y | V67: Y | X67: Not started | Y67: https://www.mutinyhq.com/blog/best-tools-to-create-pricing-proposals
A68: /blog/best-tools-to-create-sales-pitch-decks | B68: blog | C68: P1 | D68: fix | E68: current | F68: 7 | G68: SPP (Sales Presentations and Proposals) | H68: 3 | I68: 1 | J68: Best tools to create sales pitch decks in 2026 (AI sales presentation tools) | K68: Enterprise 'starting at $30k' (should be $40k) • Stats (Aaker 63%/5%, Storydoc 47%/2.3x, Gartner 17%/61%) not linked • No body hyperlinks to the referenced guides, pitch deck blueprint or AE page • FAQ 'What is a sales pitch deck?' repeated 3 times • 'top-rated AI tool' unsourced | L68: Fix $30k to $40k, link every stat source, and add internal links to /blueprints/pitch-deck, /use-cases/account-executives and the sibling SPP posts. Dedupe the FAQ. | N68: Last updated: July 2026 | O68: Y | P68: Y | Q68: Y | R68: N | S68: Y | T68: N | U68: Y | V68: Y | X68: Not started | Y68: https://www.mutinyhq.com/blog/best-tools-to-create-sales-pitch-decks
A69: /blog/highspot-alternatives-8-platforms-b2b-teams-evaluate-in-2026 | B69: blog | C69: P1 | D69: fix | E69: current | F69: 6 | G69: SE (Sales Enablement) | H69: 2 | I69: 3 | J69: Highspot alternatives: 9 platforms B2B teams evaluate in 2026 | K69: Slug says 8, title/meta say 9, and the meta names only 8 (Dock missing) • Intro ranks Mutiny #1; body lists it #9 • Mutiny pricing 'Account-priced, ~$30K+' and 'priced by accounts under management' contradicts /pricing (seats/credits, Enterprise from $40k) • 'top-rated AI tool' unsourced • 'Mutiny vs Highspot' mentioned but not linked • Implementation timelines (8-12 weeks etc.) unsourced • No date | L69: Fix the pricing model and $40k figure, make Mutiny's #1 placement consistent, and position it as the sales assistant that replaces legacy enablement (per the homepage). Move to a '-9-' slug with a 301, fix the meta list, add a date, and link a Mutiny vs Highspot page. Best Sales Enablement topic lever. | M69: 1:1 ABM pages, personalized landing page, microsite, or outreach asset | O69: Y | P69: Y | Q69: Y | R69: N | S69: N | T69: Y | U69: N | V69: Y | X69: Not started | Y69: https://www.mutinyhq.com/blog/highspot-alternatives-8-platforms-b2b-teams-evaluate-in-2026
A70: /blog/how-are-b2b-sales-teams-using-ai-in-2026 | B70: blog | C70: P1 | D70: fix | E70: current | F70: 7 | G70: ASA (AI Sales Assistants), GTM (AI GTM Stack), SE (Sales Enablement), CALL (Sales Call Notes and Recording) | H70: 2 | I70: 3 | J70: How are B2B sales teams using AI in 2026? | K70: Generic sitewide meta description • Internal links /blog/best-ai-sales-tools and /blog/ai-sales-agents use wrong slugs (likely 404) • Anchor 'how sales teams use AI for deal rooms and follow-ups' links to /customers instead of that post • Several stats come from weak secondary sources (prospeo, knkoutbound, nimitai, marketbetter) • 'Forecast accuracy 79% vs 51%' and 'up to 40% lift' unsourced • Conversation-intelligence section names Gong/Chorus but not Mutiny's own notetaker • No visible date and no FAQ block | L70: High-value hub: write a real meta, fix the two broken blog links and the /customers anchor, and add 'Last updated' plus an FAQ block. Add Mutiny's notetaker and auto follow-ups to the conversation-intelligence and CRM sections, and swap weak sources for primary ones. | M70: Account-tailored landing pages, microsites for named accounts | O70: Y | P70: Y | Q70: N | R70: Y | S70: N | T70: Y | U70: N | V70: Y | X70: Not started | Y70: https://www.mutinyhq.com/blog/how-are-b2b-sales-teams-using-ai-in-2026
A71: /blog/how-b2b-sales-teams-use-ai-for-deal-rooms-and-follow-ups-in-2026 | B71: blog | C71: P1 | D71: fix | E71: current | F71: 7 | G71: DSR (Digital Sales Rooms), ASA (AI Sales Assistants), CALL (Sales Call Notes and Recording) | H71: 3 | I71: 2 | J71: How B2B sales teams use AI for deal rooms and follow-ups in 2026 | K71: Four '[PLACEHOLDER: confirm current pricing before publish.]' strings are live (Dock, DocSend, Qwilr, PandaDoc) • Enterprise 'starting at $30k' (should be $40k) • Links mutinyhq.com/account-executives (missing /use-cases/) and /product (legacy) • FAQ 'What is the best AI tool for building deal rooms?' duplicated • Stats from 'Mutiny's own reporting' (4.5x, 100%, 9/10, 4/5) have no source • Meta description too long | L71: Remove the four live PLACEHOLDER strings today, fix $30k to $40k, repair the /use-cases/ and /product links, and dedupe the FAQ. Closest post to the current story (call to deal room to follow-up), so keep it fresh. | N71: Last updated: July 2026 | O71: Y | P71: Y | Q71: Y | R71: Y | S71: Y | T71: Y | U71: N | V71: Y | X71: Not started | Y71: https://www.mutinyhq.com/blog/how-b2b-sales-teams-use-ai-for-deal-rooms-and-follow-ups-in-2026
A72: /blog/how-mutiny-gives-every-seller-a-full-creative-team-with-claude | B72: blog | C72: P1 | D72: fix | E72: current | F72: 0 | G72: ASA (AI Sales Assistants), GTM (AI GTM Stack) | H72: 0 | I72: 0 | J72: How Mutiny gives every seller a full creative team with Claude | K72: Post body is empty: only the H1, author and footer render • Featured in the top 4 of the /blog index • Generic sitewide meta description | L72: Restore the missing body (likely a broken CMS embed) or unpublish it and remove it from the blog index feature slot. Add a specific meta description. | O72: N | P72: N | Q72: N | R72: N | S72: N | T72: N | U72: N | V72: Y | X72: Not started | Y72: https://www.mutinyhq.com/blog/how-mutiny-gives-every-seller-a-full-creative-team-with-claude
A73: /blog/how-to-build-a-great-deal-room-(step-by-step | B73: blog | C73: P1 | D73: fix | E73: current | F73: 8 | G73: DSR (Digital Sales Rooms) | H73: 3 | I73: 2 | J73: How to build a great deal room (step by step) | K73: FETCH: the listed URL (missing closing ')') returned an empty page; content audited from the canonical /blog/how-to-build-a-great-deal-room-(step-by-step) • Parentheses in the slug are fragile; the best-tools post links a '-step-by-step' variant (404 risk) • Links mutinyhq.com/account-executives and /sales-leaders (missing /use-cases/) • 'deal room blueprint' links /discover instead of /blueprints/deal-room • FAQ 'What should a deal room include?' repeated 3 times • 'top-rated AI tool' unsourced; no visible date | L73: Move to a clean slug (/blog/how-to-build-a-deal-room) with 301s from the '(step-by-step)', truncated and '-step-by-step' variants, and fix the sitemap entry. Repair the /use-cases/ links, add a date, dedupe the FAQ; consider H1 'How do you build a great deal room?'. | O73: Y | P73: Y | Q73: Y | R73: Y | S73: N | T73: Y | U73: Y | V73: Y | X73: Not started | Y73: https://www.mutinyhq.com/blog/how-to-build-a-great-deal-room-(step-by-step
A74: /blog/how-to-measure-abm | B74: blog | C74: P1 | D74: fix | E74: mixed | F74: 5 | H74: 0 | I74: 2 | J74: How to Measure ABM: Metrics That Prove ROI | K74: Promotes 'Account Intelligence' and web extension as current products; links /product/account-intelligence and CTA /product (old URLs) • 'Mutiny's Revenue Alignment Report' link points to a _next/image .jpg, not a report • Intro says 'in 2025', later heading says 'in 2026' • Customer stats (LaunchDarkly 45 meetings/150%, Andela 14x, Snowflake 80% higher ACV) link to old /playbooks URLs; verify live • Links /blog/abm-automation and /playbooks/* (legacy) • No visible date | L74: Remove Account Intelligence/web-extension product claims and old /product and /playbooks links; replace the closing Mutiny section with how the sales assistant gives reps and leaders shared account context. Fix the 2025/2026 mismatch and broken report link, add an updated date and a short FAQ. | M74: Mutiny's Account Intelligence, hyper-personalized landing pages, via the web extension, power 1:1 personalization, ABM-first framing throughout | O74: Y | P74: N | Q74: N | R74: Y | S74: N | T74: Y | U74: Y | V74: Y | X74: Not started | Y74: https://www.mutinyhq.com/blog/how-to-measure-abm
A75: /blog/mutiny-vs-claude.-when-gtm-teams-need-an-application-not-just-a-foundation-model | B75: blog | C75: P1 | D75: fix | E75: mixed | F75: 6 | G75: ASA (AI Sales Assistants), GTM (AI GTM Stack) | H75: 2 | I75: 2 | J75: Mutiny vs Claude. When GTM Teams Need an Application, Not Just a Foundation Model | K75: Meta description is the generic homepage tagline • Cost row 'Per-surface or per-seat annual contract' conflicts with /pricing (Free, Business $50/mo, Enterprise from $40k) • Typos: 'to informs teams', 'a major addition property', 'is is in the account context', 'but primarily used Claude' • Claude pricing/model names (Sonnet 4.6 $3/$15) have no as-of date • Descriptors 'GTM application' and 'activation layer for GTM' instead of 'sales assistant'; no notetaker or call follow-up story • No date shown | L75: Write a page-specific meta and retitle 'Mutiny vs Claude: do sales teams need an AI sales assistant or just a model?'; lead with the rep workflow (notetaker, auto follow-ups, Mutiny MCP inside Claude) before ABM. Fix the pricing row and typos, add an updated date and links to /enterprise and /use-cases/account-executives. | M75: 1:1 ABM page generation, ABM pages, 'Where Mutiny wins for marketing teams' placed before sales | O75: N | P75: Y | Q75: Y | R75: N | S75: N | T75: N | U75: N | V75: Y | X75: Not started | Y75: https://www.mutinyhq.com/blog/mutiny-vs-claude.-when-gtm-teams-need-an-application-not-just-a-foundation-model
A76: /blog/mutiny-vs-highspot.-a-complete-guide-on-the-old-vs-new-way-of-enabling-sellers | B76: blog | C76: P1 | D76: fix | E76: current | F76: 6 | G76: SE (Sales Enablement) | H76: 2 | I76: 3 | J76: Mutiny vs Highspot. A complete guide on the old vs new way of enabling sellers | K76: Pricing row 'Free to start. Per-seat annual contract' conflicts with /pricing tiers • '40% of sales enablement implementations considered failures (Sybill)' is unlinked here and sourced to a vendor blog • Highspot '$40 to $90 per seat per month' unsourced • Highspot-Seismic merger (Feb 2026) asserted without a link here; verify • Descriptors 'generation layer' / 'AI-native sales generation platform' instead of 'sales assistant' • Meta about 300 chars (truncates) • No date shown | L76: Retitle 'Mutiny vs Highspot: which is better for sales enablement in 2026?', trim the meta under 160 chars, add an updated date, fix the pricing row, and source Highspot pricing and the merger. Add a comparison row for call notetaking and automatic follow-ups, and link /enterprise and /use-cases/sales-leaders. | O76: N | P76: Y | Q76: Y | R76: Y | S76: N | T76: N | U76: N | V76: Y | X76: Not started | Y76: https://www.mutinyhq.com/blog/mutiny-vs-highspot.-a-complete-guide-on-the-old-vs-new-way-of-enabling-sellers
A77: /blog/mutiny-vs-seismic.-the-sales-enablement-library-was-built-for-a-problem-we-no-longer-have | B77: blog | C77: P1 | D77: fix | E77: current | F77: 6 | G77: SE (Sales Enablement) | H77: 2 | I77: 3 | J77: Mutiny vs Seismic. The Sales Enablement Library Was Built for a Problem We No Longer Have | K77: Factual error: 'Seismic and Hubspot just announced their merger'; should be Highspot • Typos: '65% of content marketing creates goes unused', 'replace your your DAM', 'growing.The next', 'a different content' • Pricing row 'Free to start. Per-seat annual contract' conflicts with /pricing • '$6B in investment' and Seismic per-seat pricing unsourced • Meta description is the generic homepage tagline • No date | L77: Change 'Hubspot' to 'Highspot' now, write a page-specific meta, and fix the typos and pricing row. Retitle 'Mutiny vs Seismic: is a sales enablement library still worth it in 2026?' with an updated date and links to /enterprise and /use-cases/sales-leaders. | O77: N | P77: Y | Q77: Y | R77: Y | S77: N | T77: N | U77: N | V77: Y | X77: Not started | Y77: https://www.mutinyhq.com/blog/mutiny-vs-seismic.-the-sales-enablement-library-was-built-for-a-problem-we-no-longer-have
A78: /blog/our-engineering-values | B78: blog | C78: P1 | D78: fix | E78: legacy | F78: 1 | H78: 0 | I78: 0 | J78: Our Engineering Values | K78: Meta and intro describe Mutiny as personalization tools for marketing teams • 'just over two years', '100M requests a month' outdated • Brex, Segment, Carta named as customers (legacy era) • Careers CTA goes to apply.workable.com; site uses /join-us | L78: Quick fix: rewrite the first paragraph and meta to describe Mutiny as the sales assistant built for customer-facing work, drop the dated scale/customer claims, and point the hiring CTA to /join-us. The values content itself can stay. | M78: provides marketing teams with world class personalization tools, create engaging experiences for their customers, all without engineering | O78: N | P78: N | Q78: N | R78: N | S78: N | T78: N | U78: N | V78: Y | X78: Not started | Y78: https://www.mutinyhq.com/blog/our-engineering-values
A79: /blog/seismic-alternatives-8-platforms-enterprise-b2b-teams-evaluate-in-2026 | B79: blog | C79: P1 | D79: fix | E79: mixed | F79: 6 | G79: SE (Sales Enablement), DSR (Digital Sales Rooms) | H79: 1 | I79: 2 | J79: Seismic alternatives: 9 platforms enterprise B2B teams evaluate in 2026 | K79: Pricing wrong: '~$30K+ enterprise' and 'Enterprise starting around $30K' (truth: from $40,000/yr) • Intro answer lists Mutiny twice ('Mutiny, Dock, ... Spekit, Mutiny, and Bloomfire') • Count mismatch: slug says 8, title/meta say 9, key takeaways say 'The 8 alternatives'; meta omits Dock • 'Mutiny pricing is account-based rather than per-rep' contradicts per-seat/credit pricing on /pricing • Mutiny implementation '4 to 6 weeks' here vs 'a few days' in other posts • Mutiny described only as landing page/microsite generator; no notetaker, follow-ups or sales assistant • FAQ cites DocSend which is not in the list • Unsourced claims: 12-week implementations, compliance comparisons | L79: High-value Sales Enablement page (Seismic owns 61% of SE answers). Fix the duplicate Mutiny/8-vs-9 counts and $30K pricing, and rewrite the Mutiny entry as the sales assistant (notetaker, follow-ups, deal rooms, business cases) instead of landing pages/microsites. Add a visible updated date and source the implementation-time claims. | M79: fully personalized landing page, microsite, or outreach asset for a named target account, Enterprise teams running ABM or named-account motions, Agentic personalized content, the personalization layer | O79: Y | P79: Y | Q79: Y | R79: N | S79: N | T79: Y | U79: N | V79: Y | X79: Not started | Y79: https://www.mutinyhq.com/blog/seismic-alternatives-8-platforms-enterprise-b2b-teams-evaluate-in-2026
A80: /blog/the-15-best-ai-sales-agents-for-b2b-teams-in-2026 | B80: blog | C80: P1 | D80: fix | E80: current | F80: 6 | G80: ASA (AI Sales Assistants) | H80: 2 | I80: 2 | J80: The 15 Best AI Sales Agents for B2B Teams in 2026 | K80: Pricing wrong: 'Enterprise custom plans (starting at $30k)' (truth: from $40,000/yr) • Garbled and unsourced: 'Gong is that 40% of Gong customers also use Clari' • Mutiny 'Skip this if ... call analytics (Gong is the right tool)' contradicts notetaker-on-every-call positioning • BMC/Snowflake/Rippling customer links all point to the homepage • Duplicate FAQ: 'What's the difference between an AI sales tool and an AI sales agent?' appears twice • Meta description gives no answer; overlaps heavily with 3 other 'best AI sales agents' posts (cannibalization) | L80: Consolidate with /blog/top-ai-sales-agents-for-2026 (pick one canonical AI Sales Assistants listicle and 301 the other). Fix $30k pricing, the garbled Gong/Clari line and duplicate FAQ, and reposition Mutiny as the sales assistant that records calls and drafts follow-ups/CRM updates. Add a 40-60 word answer listing the agents under the H1. | M80: ABM campaigns, ABM landing pages | N80: as of May 2026 (in text, no visible updated date) | O80: Y | P80: N | Q80: Y | R80: Y | S80: Y | T80: Y | U80: N | V80: Y | X80: Not started | Y80: https://www.mutinyhq.com/blog/the-15-best-ai-sales-agents-for-b2b-teams-in-2026
A81: /blog/the-best-abm-tools-in-2026-a-buyer-s-guide-for-b2b-gtm-teams | B81: blog | C81: P1 | D81: fix | E81: mixed | F81: 6 | H81: 0 | I81: 1 | J81: The best ABM tools in 2026: A buyer's guide for B2B GTM teams | K81: Meta description is the generic homepage tagline • Pricing wrong: 'Enterprise custom plans (starting at $30k)' • Says 'The 8 best ABM tools' but profiles 9 (Crustdata #9); FAQ answer lists 8 • Duplicate FAQ: 'How much do ABM platforms cost?' twice • Contradiction: Mutiny time to value '30-45 days' vs FAQ 'a few days' • Unsourced FAQ stats: 137% ROI, 49.2%, 64.1%, 84%, 78.7%, $3.81B market • 'Category leader' claim unsupported | L81: Keep for ABM traffic but stop calling Mutiny 'the category leader for AI-native account personalization'; describe it as the sales assistant whose assets (deal rooms, business cases, 1:1 pages) support ABM. Fix meta, $30k pricing, 8-vs-9 count, duplicate FAQ, and source or cut the FAQ stats. | M81: The category leader for AI-native account personalization, account-tailored landing pages, microsites, buyer-facing personalization layer of a modern ABM stack, personalization at scale | O81: Y | P81: Y | Q81: Y | R81: Y | S81: N | T81: Y | U81: N | V81: Y | X81: Not started | Y81: https://www.mutinyhq.com/blog/the-best-abm-tools-in-2026-a-buyer-s-guide-for-b2b-gtm-teams
A82: /blog/the-best-ai-agents-for-b2b-sales-in-2026-what-s-real-vs.-hype | B82: blog | C82: P1 | D82: fix | E82: current | F82: 6 | G82: ASA (AI Sales Assistants) | H82: 2 | I82: 2 | J82: The best AI agents for B2B sales in 2026: What's real vs. hype | K82: Pricing wrong: 'Enterprise custom plans (starting at $30k)' • Count mismatch: heading and table say 10, 12 agents profiled (Default, Consensus added); meta lists 11; FAQ omits Default and Consensus • Mutiny 'Memory: learns from which assets ... produce engagement and pipeline movement' is unverified • Says Mutiny does not do 'CRM automation', contradicting CRM updates in launch post • Credits MCP to Outreach as the emerging standard without mentioning Mutiny MCP • 'Acquired June 2026' capitalization; meta has no ending punctuation | L82: Fix counts (10 vs 12) in H2, table, meta and FAQ, and correct pricing. Update the Mutiny entry to the sales-assistant story (notetaker, follow-ups, CRM updates, Mutiny MCP) and add a visible updated date. | M82: landing pages | O82: Y | P82: Y | Q82: Y | R82: Y | S82: N | T82: Y | U82: N | V82: Y | X82: Not started | Y82: https://www.mutinyhq.com/blog/the-best-ai-agents-for-b2b-sales-in-2026-what-s-real-vs.-hype
A83: /blog/the-best-ai-sales-agents-for-aes-in-2026 | B83: blog | C83: P1 | D83: fix | E83: current | F83: 8 | G83: ASA (AI Sales Assistants), CALL (Sales Call Notes and Recording) | H83: 3 | I83: 1 | J83: The best AI sales agents for AEs in 2026 | K83: False product claim: Mutiny 'does not record calls' (truth: notetaker on every call) • Pricing wrong: 'Enterprise custom plans (starting at $30k)' • FAQ 'What is the difference between an AI sales agent and an AI sales tool?' appears 3 times • 'Top-rated AI tool' claim unsourced • Vanta (Celeste Cote) and Kaizen (Jeff Goldberg) quotes are not in the confirmed customer list; verify permission • 'Over 70% of their time on non-selling work' conflicts with 60% used in other posts • Meta description is ~400 characters | L83: Best AE-persona post in this batch, but it states Mutiny does not record calls. Rewrite the Mutiny entry and 'pairs with Gong' workflow around the built-in notetaker, fix pricing, dedupe the FAQ and trim meta to ~155 characters. | M83: 1:1 ABM pages | N83: Last updated: July 2026 | O83: Y | P83: Y | Q83: Y | R83: Y | S83: Y | T83: Y | U83: N | V83: Y | X83: Not started | Y83: https://www.mutinyhq.com/blog/the-best-ai-sales-agents-for-aes-in-2026
A84: /blog/the-best-ai-sales-enablement-products-for-b2b-startups-in-2026 | B84: blog | C84: P1 | D84: fix | E84: current | F84: 8 | G84: SE (Sales Enablement) | H84: 2 | I84: 2 | J84: The best AI sales enablement products for B2B startups in 2026 | K84: Live draft note on page: '[PLACEHOLDER: confirm current Clay plan pricing before publishing.]' • Pricing wrong: 'Enterprise custom plans (starting at $30k)' • FAQ 'What is AI sales enablement?' appears 3 times • Says Mutiny 'does not store and govern a large approved-content library', contradicting launch post 'We reinvented the content library' • Key stat cites a 2024 Salesforce page | L84: Remove the visible PLACEHOLDER note immediately, fix $30k pricing and the triple FAQ. Align the 'does not store a content library' line with the current product (content library + engagement tracking) and add the notetaker. | M84: 1:1 ABM pages | N84: Last updated: July 2026 | O84: Y | P84: Y | Q84: Y | R84: Y | S84: Y | T84: Y | U84: Y | V84: Y | X84: Not started | Y84: https://www.mutinyhq.com/blog/the-best-ai-sales-enablement-products-for-b2b-startups-in-2026
A85: /blog/the-best-ai-sales-tools-in-2026-a-buyer-s-guide-for-b2b-gtm-teams | B85: blog | C85: P1 | D85: fix | E85: mixed | F85: 7 | G85: ASA (AI Sales Assistants), SE (Sales Enablement), GTM (AI GTM Stack) | H85: 1 | I85: 2 | J85: The best AI sales tools in July 2026: A buyer's guide for B2B GTM teams | K85: Meta description repeats its first sentence, lists 12 vs 13 tools, and has typo 'what too does' • 'Last updated: July 2026' rendered twice (once as an H2) • Missing line break merges 'What makes an AI sales tool the best' H2 into a bullet • Typo: 'perosnalization' • FAQ 'How much should we budget for AI sales tools?' appears 3 times • Pricing wrong: 'Enterprise custom plans (starting at $30k)' • 'Chorus: The Salesforce-native alternative' (Chorus is ZoomInfo) • FAQ claims for ABM teams 'top-of-funnel volume is the binding constraint', contradicting body • 'Only tool rebuilt from scratch for the agentic era' unverifiable | L85: This is the pillar other posts link to and it is pinned on /blog, so fix it first: rewrite meta, remove the duplicate date H2 and triple FAQ, fix typos, Chorus label and $30k pricing. Reframe Mutiny from 'account personalization/ABM' to the sales assistant and drop 'July' from the H1 so it does not age. | M85: account personalization, 1:1 ABM pages, named-account or ABM motions, account-based campaigns | N85: Last updated: July 2026 | O85: Y | P85: Y | Q85: Y | R85: Y | S85: Y | T85: Y | U85: N | V85: Y | X85: Not started | Y85: https://www.mutinyhq.com/blog/the-best-ai-sales-tools-in-2026-a-buyer-s-guide-for-b2b-gtm-teams
A86: /blog/the-best-ai-tools-for-account-executives-in-2026-a-buyer-s-guide-for-b2b-sales-teams | B86: blog | C86: P1 | D86: fix | E86: current | F86: 7 | G86: ASA (AI Sales Assistants), CALL (Sales Call Notes and Recording) | H86: 3 | I86: 1 | J86: The best AI tools for account executives in 2026: A buyer's guide for B2B sales teams | K86: False product claim: Mutiny 'does not record calls' • Count chaos: intro lists 12 incl. Dooly, H2 says 11, text says 'The 10 tools below', table titled 10 with 11 rows, FAQ says 'All 10 tools'; Dooly never profiled • Pricing wrong: 'Enterprise custom plans (starting at $30k)' • Salesmotion entry reads like paid copy with unsourced 'sales velocity 42%' stat • Promotes Otter.ai and Sybill for call notes with no mention of Mutiny's own notetaker | L86: Fix the tool counts and Dooly references, correct pricing, and replace 'does not record calls' with the notetaker story (it competes with Otter/Sybill in the same list). Consider merging with /blog/the-best-ai-sales-agents-for-aes-in-2026 to stop two AE listicles splitting citations. | M86: account-tailored landing pages, account-specific landing page or one-pager | O86: Y | P86: Y | Q86: Y | R86: Y | S86: N | T86: Y | U86: Y | V86: Y | X86: Not started | Y86: https://www.mutinyhq.com/blog/the-best-ai-tools-for-account-executives-in-2026-a-buyer-s-guide-for-b2b-sales-teams
A87: /blog/the-best-ai-tools-to-close-more-deals-in-2026 | B87: blog | C87: P1 | D87: fix | E87: current | F87: 7 | G87: DSR (Digital Sales Rooms), ASA (AI Sales Assistants) | H87: 3 | I87: 2 | J87: The best AI tools to close more deals in 2026 | K87: Pricing wrong: 'Enterprise custom plans (starting at $30k)' • Duplicate FAQ: 'How are sales teams using AI for deal rooms and follow-ups?' twice • Key rep-time stat links a 2024 Salesforce page • 'Rebuilt from scratch for the agentic era' unverifiable • Says reps 'turn call recordings into recaps' but never states Mutiny records the calls • Meta ~380 characters | L87: Fix pricing, duplicate FAQ and meta length; add the notetaker and auto follow-ups to the Mutiny entry. Swap the 2024 Salesforce stat for the 2026 State of Sales figure already used elsewhere. | M87: account-based campaigns | N87: Last updated: July 2026 | O87: Y | P87: Y | Q87: Y | R87: Y | S87: Y | T87: Y | U87: N | V87: Y | X87: Not started | Y87: https://www.mutinyhq.com/blog/the-best-ai-tools-to-close-more-deals-in-2026
A88: /blog/the-best-sales-enablement-tools-in-2026-a-buyer-s-guide-for-b2b-sales-teams | B88: blog | C88: P1 | D88: fix | E88: current | F88: 8 | G88: SE (Sales Enablement) | H88: 2 | I88: 3 | J88: The best sales enablement tools in 2026: A buyer's guide for B2B sales teams | K88: Pricing wrong: 'Enterprise custom plans (starting at $30k)' • Unsourced: '49% win rate on forecasted deals, compared with 42.5%' • '55% of sales leaders plan to increase enablement budgets' is spun as a reason for Mutiny • False product claim: Mutiny does not 'provide conversation intelligence' (truth: notetaker on every call) • 'Category leader for AI-generated sales content' unsupported • Implementation 'a few days' vs '4 to 6 weeks' on the Seismic alternatives post | L88: Highest-value Sales Enablement asset in the batch (Mutiny 3.7% vs Seismic 61%). Fix pricing, source or cut the 49%/42.5% stat, and replace the 'does not provide conversation intelligence' and 'generation not library' lines with the current story: notetaker, playbooks, content library, replace legacy enablement tools. | M88: 1:1 ABM pages, account-tailored landing pages, account-specific landing page for outreach | N88: Last updated: July 2026 | O88: Y | P88: Y | Q88: Y | R88: Y | S88: Y | T88: Y | U88: Y | V88: Y | X88: Not started | Y88: https://www.mutinyhq.com/blog/the-best-sales-enablement-tools-in-2026-a-buyer-s-guide-for-b2b-sales-teams
A89: /blog/top-ai-sales-agents-for-2026 | B89: blog | C89: P1 | D89: fix | E89: current | F89: 7 | G89: ASA (AI Sales Assistants) | H89: 2 | I89: 2 | J89: Top AI sales agents for 2026 | K89: Two live draft notes: '[PLACEHOLDER: verify Gong 2026 ARR or customer-count figure ...]' and '[PLACEHOLDER: verify Lavender's currently published reply-rate ...]' • Pricing wrong: 'Enterprise custom plans (starting at $30k)' • FAQ 'What is an AI sales agent?' appears 3 times • Meta lists 6 tools in 3 categories; body has 14+ agents in more categories • Lists Drift as a standalone agent (absorbed into Salesloft) • 'Teams see 4.5x faster asset creation' stated without the 'Mutiny's own reporting' caveat | L89: Remove both PLACEHOLDER notes now. Make this the canonical AI Sales Assistants listicle (301 /blog/the-15-best-ai-sales-agents-for-b2b-teams-in-2026 here), fix pricing and the triple FAQ, and rewrite the meta to match the body. | M89: 1:1 ABM pages | N89: Last updated: July 2026 | O89: Y | P89: Y | Q89: Y | R89: Y | S89: Y | T89: Y | U89: N | V89: Y | X89: Not started | Y89: https://www.mutinyhq.com/blog/top-ai-sales-agents-for-2026
A90: /blog/what-ai-tools-help-sellers-create-deal-specific-content | B90: blog | C90: P1 | D90: fix | E90: current | F90: 6 | G90: SPP (Sales Presentations and Proposals), DSR (Digital Sales Rooms), SE (Sales Enablement) | H90: 3 | I90: 1 | J90: What AI tools help sellers create deal-specific content? | K90: Pricing wrong: 'Enterprise (custom, from $30k)' • McKinsey 'less than 30% of time' stat has no link • Internal links use http:// non-www (http://mutinyhq.com/product etc.) • Positions Gong as the call-context source for Mutiny; omits Mutiny's own notetaker | L90: Strong AEO structure. Fix pricing, link the McKinsey stat, switch links to https://www, add a visible date, and state that Mutiny captures the call itself rather than depending on Gong. | O90: Y | P90: Y | Q90: Y | R90: N | S90: N | T90: Y | U90: Y | V90: Y | X90: Not started | Y90: https://www.mutinyhq.com/blog/what-ai-tools-help-sellers-create-deal-specific-content
A91: /blog/what-ai-tools-should-every-bdr-and-ae-have | B91: blog | C91: P1 | D91: fix | E91: current | F91: 7 | G91: ASA (AI Sales Assistants) | H91: 3 | I91: 1 | J91: What AI tools should every BDR and AE have? | K91: Pricing wrong: 'Enterprise (custom, from $30k)' • FAQ 'What is the difference between AI tools for BDRs and AI tools for AEs?' appears 3 times • Draft-note tone left in copy: 'This is the tool that the existing BDR/AE listicles are missing' • Dead reference: 'see Best AI sales tools for enterprise B2B teams' (unlinked, no such post) • Clari '98% forecast accuracy' unsourced; Apollo pricing ($49/$79) inconsistent with other posts • http:// internal links | L91: Fix pricing, triple FAQ, the draft-note sentence and the dead 'enterprise' reference (link to the best AI sales tools pillar). Add the notetaker so Mutiny covers the conversation layer too, and add a date. | O91: Y | P91: Y | Q91: Y | R91: Y | S91: N | T91: Y | U91: Y | V91: Y | X91: Not started | Y91: https://www.mutinyhq.com/blog/what-ai-tools-should-every-bdr-and-ae-have
A92: /blog/what-gtm-stack-does-a-series-b-saas-company-actually-need-for-sales-content-in-2026 | B92: blog | C92: P1 | D92: fix | E92: current | F92: 4 | G92: GTM (AI GTM Stack) | H92: 1 | I92: 3 | J92: What GTM Stack Does a Series B SaaS Company Actually Need for Sales Content in 2026? | K92: Meta description is the generic homepage tagline • Forrester '65% of B2B content goes unused' links to forrester.com homepage (unsourced) • No 40-60 word direct answer under the H1 • Workflow says 'Gong transcribes it' then rep opens Mutiny, ignoring Mutiny's own notetaker • '33% of time selling' vs 30%/40% used in sibling posts | L92: Close to the AI GTM Stack topic where Mutiny has 0.5% vs Clay 47%. Add a direct answer naming the 6 layers, a real meta, a date and a proper Forrester source, and redraw Layer 4/5 so Mutiny is the assistant that records calls and produces the assets. | M92: ABM campaigns (landing pages, microsites, ads) | O92: Y | P92: N | Q92: Y | R92: N | S92: N | T92: Y | U92: N | V92: Y | X92: Not started | Y92: https://www.mutinyhq.com/blog/what-gtm-stack-does-a-series-b-saas-company-actually-need-for-sales-content-in-2026
A93: /blog/what-is-an-ai-sales-agent | B93: blog | C93: P1 | D93: fix | E93: current | F93: 5 | G93: ASA (AI Sales Assistants) | H93: 2 | I93: 2 | J93: What is an AI sales agent? | K93: Meta description is the generic homepage tagline • Broken link: 'guide to the top AI sales agents for 2026' points to /blog/ai-sales-agents, which returns an empty page (should be /blog/top-ai-sales-agents-for-2026) • Link text 'mutinyhq.com/account-executives' and 'mutinyhq.com/product' both point to the homepage • Lists Drift as a standalone qualification agent | L93: Strong definitional page for AI Sales Assistants (Mutiny ~0%). Write a real meta, fix the 3 broken/mismatched links, add a date, and add Mutiny as the assistive agent example (sales assistant) in the autonomous vs assistive table. | O93: Y | P93: Y | Q93: Y | R93: Y | S93: N | T93: N | U93: N | V93: Y | X93: Not started | Y93: https://www.mutinyhq.com/blog/what-is-an-ai-sales-agent
A94: /blueprints/1-1-abm | B94: blueprint | C94: P1 | D94: fix | E94: mixed | F94: 5 | H94: 2 | I94: 1 | J94: 1:1 ABM | K94: Visible editor note on the live page: '(Editor: deep-link each name to its inner blueprint page.)' • Descriptor 'the GTM agent built for customer-facing work and workflow automation' instead of 'sales assistant' • '4.5x faster with 100% design satisfaction' and 'personalized pages drive higher engagement than traditional outbound' are unsourced • Title tag is just 'Mutiny'; generic meta • H1 renders after the body content | L94: Delete the editor note, swap the descriptor to 'the sales assistant built for customer-facing work', and attribute or remove the 4.5x/100% stat. Set title 'What Is a 1:1 ABM Page? Template + Examples | Mutiny' with a unique meta and move the H1 above the definition. | M94: 'personalized landing page built for a single target account', 'Mutiny's broader account-based marketing toolkit' | N94: July 15, 2026 | O94: N | P94: Y | Q94: Y | R94: Y | S94: N | T94: Y | U94: N | V94: Y | X94: Not started | Y94: https://www.mutinyhq.com/blueprints/1-1-abm
A95: /blueprints/case-study | B95: blueprint | C95: P1 | D95: fix | E95: current | F95: 5 | G95: SE (Sales Enablement) | H95: 2 | I95: 1 | J95: Case Study | K95: FAQ: 'Enterprise custom plans (starting at $30k)' conflicts with /pricing ($40,000/yr Enterprise, $50/mo Business) • Descriptor 'GTM agent built for customer-facing work and workflow automation' • '4.5x faster with 100% design satisfaction' unsourced • Body link to old slug /products/beautiful-assets • Title 'Mutiny'; generic meta; no date | L95: Change the pricing FAQ to the /pricing truth (Free $0, Business $50/mo, Enterprise from $40,000/yr), fix the descriptor and the old product link, and attribute the 4.5x stat. Add title 'How to Write a B2B Case Study (Template) | Mutiny', a unique meta and a visible updated date. | O95: N | P95: Y | Q95: Y | R95: Y | S95: N | T95: Y | U95: N | V95: Y | X95: Not started | Y95: https://www.mutinyhq.com/blueprints/case-study
A96: /blueprints/cold-outreach | B96: blueprint | C96: P1 | D96: fix | E96: current | F96: 5 | G96: SE (Sales Enablement), GTM (AI GTM Stack) | H96: 3 | I96: 2 | J96: Cold Outreach | K96: FAQ: Enterprise 'starting at $30k' (pricing page: $40,000/yr); Business implied custom • Descriptor 'GTM agent built for customer-facing work and workflow automation' • '4.5x faster with 100% design satisfaction' unsourced • Quote from Celeste Cote, Account Executive, Vanta: Vanta is not on the named-customer list; confirm approval • Title 'Mutiny'; generic meta | L96: Fix the pricing FAQ to the /pricing page, swap the descriptor, attribute or drop the 4.5x stat and confirm the Vanta quote is approved. Title 'How to Write Cold Outreach That Gets Replies (Template) | Mutiny', unique meta, link the outbound chapter. | N96: July 15, 2026 | O96: N | P96: Y | Q96: Y | R96: Y | S96: N | T96: Y | U96: N | V96: Y | X96: Not started | Y96: https://www.mutinyhq.com/blueprints/cold-outreach
A97: /blueprints/competitive-comparison | B97: blueprint | C97: P1 | D97: fix | E97: current | F97: 5 | G97: SE (Sales Enablement) | H97: 3 | I97: 2 | J97: Competitive Comparison | K97: FAQ: Enterprise 'starting at $30k' conflicts with /pricing • Descriptor 'GTM agent...'; unsourced 4.5x/100% stat • Kevin Jong titled 'Principal GTM AI Operator' here but 'Principal AI GTM Operator' on the Genesis case study • Title 'Mutiny'; generic meta; no date | L97: Fix pricing, descriptor and Kevin Jong's title, attribute the 4.5x stat, add an updated date. Title 'Competitive Comparison Page Template (vs. Battlecard) | Mutiny' and a unique meta; practice what it preaches by linking real Mutiny vs Highspot/Seismic pages. | O97: N | P97: Y | Q97: Y | R97: Y | S97: N | T97: Y | U97: N | V97: Y | X97: Not started | Y97: https://www.mutinyhq.com/blueprints/competitive-comparison
A98: /blueprints/deal-room | B98: blueprint | C98: P1 | D98: fix | E98: current | F98: 6 | G98: DSR (Digital Sales Rooms) | H98: 3 | I98: 2 | J98: Deal Room | K98: FAQ: Enterprise 'starting at $30k' conflicts with /pricing • Two separate 'Frequently asked questions' sections (pricing Q split off above Related blueprints) • Descriptor 'GTM agent...'; unsourced 4.5x/100% stat • Quote from Jeff Goldberg, Account Executive, Kaizen: Kaizen not on the named-customer list; confirm • Tagline truncated: 'keep every stakeholder aligned from first meeting.' • Title 'Mutiny'; generic meta; no date | L98: Fix pricing, merge the two FAQ blocks, swap the descriptor and finish the tagline. Title 'What Is a Digital Sales Room? Deal Room Template | Mutiny', add an updated date, a named-competitor section (Aligned, Dock, Trumpet) and a link to /assets/deal-room. | O98: N | P98: Y | Q98: Y | R98: Y | S98: N | T98: Y | U98: N | V98: Y | X98: Not started | Y98: https://www.mutinyhq.com/blueprints/deal-room
A99: /blueprints/demo-pre-read | B99: blueprint | C99: P1 | D99: fix | E99: current | F99: 5 | G99: SE (Sales Enablement), SPP (Sales Presentations and Proposals) | H99: 3 | I99: 2 | J99: Demo Pre-read | K99: FAQ: Enterprise 'starting at $30k' conflicts with /pricing • Descriptor 'GTM agent...'; unsourced 4.5x/100% stat • Title 'Mutiny'; generic meta | L99: Fix the pricing FAQ and descriptor and attribute the 4.5x stat. Title 'What Is a Demo Pre-Read? Template + Examples | Mutiny', unique meta; mention that Mutiny can send it automatically from the discovery call recording and link the demo chapter. | N99: July 15, 2026 | O99: N | P99: Y | Q99: Y | R99: Y | S99: N | T99: Y | U99: N | V99: Y | X99: Not started | Y99: https://www.mutinyhq.com/blueprints/demo-pre-read
A100: /blueprints/event-invite | B100: blueprint | C100: P1 | D100: fix | E100: mixed | F100: 4 | H100: 1 | I100: 1 | J100: Event Invite | K100: FAQ: Enterprise 'starting at $30k' conflicts with /pricing • Unique broken links: footer 'Automation' and 'Integrations' and body 'repeatable routine' all point to the homepage • Descriptor 'GTM agent...'; unsourced 4.5x/100% stat • Rippling quote about giving sellers design capabilities is unrelated to event pages • Title 'Mutiny'; generic meta | L100: Fix the pricing FAQ, point the 'routine', Automation and Integrations links to /products/automations and /products/integration, swap the descriptor. Reframe around reps inviting named accounts to field events rather than 'conversion-focused' registration pages, and use an event-relevant customer quote. | M100: 'conversion-focused event page', 'converts better than a generic registration form' | N100: July 15, 2026 | O100: N | P100: Y | Q100: Y | R100: Y | S100: N | T100: Y | U100: N | V100: Y | X100: Not started | Y100: https://www.mutinyhq.com/blueprints/event-invite
A101: /blueprints/executive-business-case | B101: blueprint | C101: P1 | D101: fix | E101: current | F101: 5 | G101: SPP (Sales Presentations and Proposals), SE (Sales Enablement) | H101: 3 | I101: 3 | J101: Executive Business Case | K101: FAQ: Enterprise 'starting at $30k' conflicts with /pricing • Two 'Frequently asked questions' sections • BMC CMO quote describes the legacy 'dynamic personalization' platform and a marketing team, on a sales business-case page • Descriptor 'GTM agent...'; unsourced 4.5x/100% stat • Competes with /assets/business-case and /chapters/executive-business-case • Title 'Mutiny'; generic meta; no date | L101: Fix pricing, merge FAQs, swap descriptor, and replace the BMC 'dynamic personalization' quote with a sales quote (Atomicwork or Netic). Title 'How to Write an Executive Business Case (Template) | Mutiny', unique meta, cross-link the asset page and the Sam Jacobs chapter. | M101: BMC quote: 'AI platform powers... dynamic personalization and sales alignment' | O101: N | P101: Y | Q101: Y | R101: Y | S101: N | T101: Y | U101: N | V101: Y | X101: Not started | Y101: https://www.mutinyhq.com/blueprints/executive-business-case
A102: /blueprints/expansion-abm-page | B102: blueprint | C102: P1 | D102: fix | E102: mixed | F102: 4 | H102: 2 | I102: 1 | J102: Expansion ABM Page | K102: FAQ: Enterprise 'starting at $30k' conflicts with /pricing • BMC legacy 'dynamic personalization' quote • Descriptor 'GTM agent...'; unsourced 4.5x/100% stat • Title 'Mutiny'; generic meta | L102: Fix pricing and descriptor, replace the BMC quote, and reframe from 'ABM page' to an account-expansion page owned by AEs/AMs (link sales-leaders, not ABM). Unique title/meta. | M102: 'Expansion ABM', 'campaigns live' as a partnership metric, BMC quote: 'dynamic personalization' | N102: July 15, 2026 | O102: N | P102: Y | Q102: Y | R102: Y | S102: N | T102: Y | U102: N | V102: Y | X102: Not started | Y102: https://www.mutinyhq.com/blueprints/expansion-abm-page
A103: /blueprints/forward-looking-strategy | B103: blueprint | C103: P1 | D103: fix | E103: current | F103: 5 | G103: SE (Sales Enablement) | H103: 2 | I103: 2 | J103: Forward Looking Strategy | K103: FAQ: Enterprise 'starting at $30k' conflicts with /pricing • Body links to old slugs /products/beautiful-assets and /products/reliable-automation • Descriptor 'GTM agent...'; unsourced 4.5x/100% stat • Title 'Mutiny'; generic meta | L103: Fix pricing, descriptor and the two body links (to /products/smart-assets and /products/automations). Title 'Forward-Looking QBR Template: Strategy Review | Mutiny' with a unique meta. | N103: July 15, 2026 | O103: N | P103: Y | Q103: Y | R103: Y | S103: N | T103: Y | U103: N | V103: Y | X103: Not started | Y103: https://www.mutinyhq.com/blueprints/forward-looking-strategy
A104: /blueprints/group-demo-follow-up | B104: blueprint | C104: P1 | D104: fix | E104: current | F104: 5 | G104: CALL (Sales Call Notes and Recording), SE (Sales Enablement) | H104: 3 | I104: 2 | J104: Group Demo Follow Up | K104: FAQ: Enterprise 'starting at $30k' conflicts with /pricing • Descriptor 'GTM agent...'; unsourced 4.5x/100% stat • Says 'drop in your transcript' and never mentions Mutiny's own notetaker that captures it • Title 'Mutiny'; generic meta | L104: Fix pricing and descriptor; state that Mutiny's notetaker records the demo and the follow-up page is generated automatically when the call ends (link /automation/meeting-follow-up). Unique title/meta. | N104: July 15, 2026 | O104: N | P104: Y | Q104: Y | R104: Y | S104: N | T104: Y | U104: N | V104: Y | X104: Not started | Y104: https://www.mutinyhq.com/blueprints/group-demo-follow-up
A105: /blueprints/impact-report | B105: blueprint | C105: P1 | D105: fix | E105: current | F105: 5 | G105: SE (Sales Enablement) | H105: 2 | I105: 2 | J105: Impact Report | K105: FAQ: Enterprise 'starting at $30k' conflicts with /pricing • Body links to old slugs /products/beautiful-assets and /products/reliable-automation • Kaizen AE quote about a champion is used on a CSM renewal page (weak fit; Kaizen not on named list) • Descriptor 'GTM agent...'; unsourced 4.5x/100% stat • Title 'Mutiny'; generic meta | L105: Fix pricing, descriptor and body links, and use a CS/renewal quote. Title 'Customer Impact Report Template for Renewals | Mutiny' and a unique meta. | M105: 'campaigns run' as example usage metric | N105: July 15, 2026 | O105: N | P105: Y | Q105: Y | R105: Y | S105: N | T105: Y | U105: N | V105: Y | X105: Not started | Y105: https://www.mutinyhq.com/blueprints/impact-report
A106: /blueprints/meeting-recap | B106: blueprint | C106: P1 | D106: fix | E106: current | F106: 6 | G106: CALL (Sales Call Notes and Recording), ASA (AI Sales Assistants) | H106: 3 | I106: 2 | J106: Meeting Recap | K106: FAQ: Enterprise 'starting at $30k' conflicts with /pricing • Descriptor 'GTM agent...'; unsourced 4.5x/100% stat • Tells users to 'drop in a transcript or your notes' instead of describing the notetaker that does it automatically (core story) • Title 'Mutiny'; generic meta; no date | L106: Fix pricing and descriptor; add one paragraph: Mutiny's notetaker joins the call and generates the recap page and follow-up email automatically, compared with Gong/Fireflies notes. Title 'How to Write a Sales Meeting Recap (Template) | Mutiny', updated date, link the automation page. | O106: N | P106: Y | Q106: Y | R106: Y | S106: N | T106: Y | U106: N | V106: Y | X106: Not started | Y106: https://www.mutinyhq.com/blueprints/meeting-recap
A107: /blueprints/pitch-deck | B107: blueprint | C107: P1 | D107: fix | E107: current | F107: 6 | G107: SPP (Sales Presentations and Proposals) | H107: 3 | I107: 2 | J107: Pitch Deck | K107: FAQ: Enterprise 'starting at $30k' conflicts with /pricing • Two 'Frequently asked questions' sections • Descriptor 'GTM agent...'; unsourced 4.5x/100% stat • Vanta quote (not on named list) reused from cold-outreach • Title 'Mutiny'; generic meta | L107: Fix pricing, merge FAQs, swap descriptor, use the Netic deck metric instead of a generic quote. Title 'Sales Pitch Deck Template: 8-Slide Structure | Mutiny', unique meta, and add a short Mutiny vs Gamma section. | N107: July 15, 2026 | O107: N | P107: Y | Q107: Y | R107: Y | S107: N | T107: Y | U107: N | V107: Y | X107: Not started | Y107: https://www.mutinyhq.com/blueprints/pitch-deck
A108: /blueprints/pricing-proposal | B108: blueprint | C108: P1 | D108: fix | E108: current | F108: 5 | G108: SPP (Sales Presentations and Proposals) | H108: 3 | I108: 2 | J108: Pricing Proposal | K108: FAQ: Enterprise 'starting at $30k' conflicts with /pricing • Same body is duplicated on /blueprints/case-study-round-up • Descriptor 'GTM agent...'; unsourced 4.5x/100% stat • Title 'Mutiny'; generic meta | L108: Fix pricing and descriptor; once the round-up page is rewritten the duplicate goes away. Title 'Pricing Proposal Template for B2B Sales | Mutiny', unique meta, link /assets/pricing-proposal and the 30MPC pricing chapter, add a Qwilr/PandaDoc comparison line. | N108: July 15, 2026 | O108: N | P108: Y | Q108: Y | R108: Y | S108: N | T108: Y | U108: N | V108: Y | X108: Not started | Y108: https://www.mutinyhq.com/blueprints/pricing-proposal
A109: /case-studies/atomicwork-enterprise-sellers-build-deal-specific-assets-in-5-minutes-with-mutiny | B109: case-study | C109: P1 | D109: fix | E109: current | F109: 5 | G109: SPP (Sales Presentations and Proposals), ASA (AI Sales Assistants), SE (Sales Enablement) | H109: 3 | I109: 2 | J109: Atomicwork's Enterprise Seller Saves 15 Hours per Week on Admin with Mutiny | K109: Headline '15 hours per week on Admin' is not derived anywhere in the body, and the story is about deck creation, not admin • URL slug says 'build deal-specific assets in 5 minutes' while the title says 15 hours/week • '15 min' stat vs body '5 minutes' / '5-10 minutes' • Quote 'used to take me 3-5 hours' vs body 'two to three hours' • Meta description is broken: 'Atomicwork,'; no H1 (title as H2 x3) | L109: Make the numbers agree (one per-deck time, one weekly total with the math shown) and retitle to what the story proves, e.g. 'Atomicwork's enterprise AE cut deck creation from 3 hours to 5 minutes'. Add a real meta, an H1, a 50-word summary box and a date; link /assets/sales-decks and /assets/pricing-proposal. | O109: N | P109: N | Q109: N | R109: Y | S109: N | T109: N | U109: N | V109: Y | X109: Not started | Y109: https://www.mutinyhq.com/case-studies/atomicwork-enterprise-sellers-build-deal-specific-assets-in-5-minutes-with-mutiny
A110: /case-studies/delphi-builds-premium-client-facing-assets-in-minutes-with-mutiny | B110: case-study | C110: P1 | D110: fix | E110: current | F110: 4 | G110: SPP (Sales Presentations and Proposals) | H110: 2 | I110: 2 | J110: Delphi Builds Premium Client-Facing Assets in Minutes with Mutiny | K110: Headline '20+ hours saved per week' vs body 'they could be saving up to 20 hours a week' (hedged estimate shown as fact) • '5min to create a landing page' vs body 'roughly three minutes' • Andrew is 'Head of Operations' early and 'Head of Creator Partnerships' later • Outdated: 'Looking Forward' says an MCP integration 'would' let agents hand off to Mutiny 'when that exists', but Mutiny MCP is now live • Typos: 'for for delivering', 'Perosnalized' (alt text), 'skeptical of what AI tools actually apply brand', 'iterations... that the time savings evaporated' • Meta broken: 'Delphi,'; no H1 | L110: Change the stat to 'up to 20 hours/week' (or the measured number), align 3 vs 5 minutes, fix Andrew's title and the typos, and update 'Looking Forward' to say the MCP integration is now available. Add a real meta, H1, summary box and date. | M110: 'custom client landing page' as headline metric | O110: N | P110: N | Q110: N | R110: Y | S110: N | T110: N | U110: N | V110: Y | X110: Not started | Y110: https://www.mutinyhq.com/case-studies/delphi-builds-premium-client-facing-assets-in-minutes-with-mutiny
...
